{
  "metadata": {
    "platform": "windows",
    "layout_name": "00000408",
    "display_name": "Greek",
    "extracted_on": "2026-07-07T00:41:44Z"
  },
  "mappings": {
    "α": [
      {
        "sequence": [
          {
            "key": "KeyA",
            "modifiers": []
          }
        ]
      }
    ],
    "8": [
      {
        "sequence": [
          {
            "key": "Digit8",
            "modifiers": []
          }
        ]
      }
    ],
    "-": [
      {
        "sequence": [
          {
            "key": "Minus",
            "modifiers": []
          }
        ]
      }
    ],
    "/": [
      {
        "sequence": [
          {
            "key": "Slash",
            "modifiers": []
          }
        ]
      }
    ],
    "}": [
      {
        "sequence": [
          {
            "key": "BracketRight",
            "modifiers": [
              "Shift"
            ]
          }
        ]
      }
    ],
    "¦": [
      {
        "sequence": [
          {
            "key": "Digit9",
            "modifiers": [
              "AltGraph"
            ]
          }
        ]
      }
    ],
    "'": [
      {
        "sequence": [
          {
            "key": "Quote",
            "modifiers": []
          }
        ]
      }
    ],
    "Ξ": [
      {
        "sequence": [
          {
            "key": "KeyJ",
            "modifiers": [
              "Shift"
            ]
          }
        ]
      }
    ],
    "=": [
      {
        "sequence": [
          {
            "key": "Equal",
            "modifiers": []
          }
        ]
      }
    ],
    "7": [
      {
        "sequence": [
          {
            "key": "Digit7",
            "modifiers": []
          }
        ]
      }
    ],
    ";": [
      {
        "sequence": [
          {
            "key": "KeyQ",
            "modifiers": []
          }
        ]
      }
    ],
    "2": [
      {
        "sequence": [
          {
            "key": "Digit2",
            "modifiers": []
          }
        ]
      }
    ],
    "&": [
      {
        "sequence": [
          {
            "key": "Digit7",
            "modifiers": [
              "Shift"
            ]
          }
        ]
      }
    ],
    "_": [
      {
        "sequence": [
          {
            "key": "Minus",
            "modifiers": [
              "Shift"
            ]
          }
        ]
      }
    ],
    "ε": [
      {
        "sequence": [
          {
            "key": "KeyE",
            "modifiers": []
          }
        ]
      }
    ],
    "Ε": [
      {
        "sequence": [
          {
            "key": "KeyE",
            "modifiers": [
              "Shift"
            ]
          }
        ]
      }
    ],
    "{": [
      {
        "sequence": [
          {
            "key": "BracketLeft",
            "modifiers": [
              "Shift"
            ]
          }
        ]
      }
    ],
    "½": [
      {
        "sequence": [
          {
            "key": "Equal",
            "modifiers": [
              "AltGraph"
            ]
          }
        ]
      }
    ],
    "π": [
      {
        "sequence": [
          {
            "key": "KeyP",
            "modifiers": []
          }
        ]
      }
    ],
    "+": [
      {
        "sequence": [
          {
            "key": "Equal",
            "modifiers": [
              "Shift"
            ]
          }
        ]
      }
    ],
    "±": [
      {
        "sequence": [
          {
            "key": "Minus",
            "modifiers": [
              "AltGraph"
            ]
          }
        ]
      }
    ],
    "»": [
      {
        "sequence": [
          {
            "key": "BracketRight",
            "modifiers": [
              "AltGraph"
            ]
          }
        ]
      }
    ],
    "¤": [
      {
        "sequence": [
          {
            "key": "Digit8",
            "modifiers": [
              "AltGraph"
            ]
          }
        ]
      }
    ],
    "|": [
      {
        "sequence": [
          {
            "key": "Backslash",
            "modifiers": [
              "Shift"
            ]
          }
        ]
      }
    ],
    "Φ": [
      {
        "sequence": [
          {
            "key": "KeyF",
            "modifiers": [
              "Shift"
            ]
          }
        ]
      }
    ],
    "Γ": [
      {
        "sequence": [
          {
            "key": "KeyG",
            "modifiers": [
              "Shift"
            ]
          }
        ]
      }
    ],
    "Λ": [
      {
        "sequence": [
          {
            "key": "KeyL",
            "modifiers": [
              "Shift"
            ]
          }
        ]
      }
    ],
    "\"": [
      {
        "sequence": [
          {
            "key": "Quote",
            "modifiers": [
              "Shift"
            ]
          }
        ]
      }
    ],
    "Χ": [
      {
        "sequence": [
          {
            "key": "KeyX",
            "modifiers": [
              "Shift"
            ]
          }
        ]
      }
    ],
    ")": [
      {
        "sequence": [
          {
            "key": "Digit0",
            "modifiers": [
              "Shift"
            ]
          }
        ]
      }
    ],
    "Ψ": [
      {
        "sequence": [
          {
            "key": "KeyC",
            "modifiers": [
              "Shift"
            ]
          }
        ]
      }
    ],
    "©": [
      {
        "sequence": [
          {
            "key": "KeyC",
            "modifiers": [
              "AltGraph"
            ]
          }
        ]
      }
    ],
    "$": [
      {
        "sequence": [
          {
            "key": "Digit4",
            "modifiers": [
              "Shift"
            ]
          }
        ]
      }
    ],
    "ς": [
      {
        "sequence": [
          {
            "key": "KeyW",
            "modifiers": []
          }
        ]
      }
    ],
    "§": [
      {
        "sequence": [
          {
            "key": "Digit5",
            "modifiers": [
              "AltGraph"
            ]
          }
        ]
      }
    ],
    "ω": [
      {
        "sequence": [
          {
            "key": "KeyV",
            "modifiers": []
          }
        ]
      }
    ],
    "ν": [
      {
        "sequence": [
          {
            "key": "KeyN",
            "modifiers": []
          }
        ]
      }
    ],
    "9": [
      {
        "sequence": [
          {
            "key": "Digit9",
            "modifiers": []
          }
        ]
      }
    ],
    "£": [
      {
        "sequence": [
          {
            "key": "Digit4",
            "modifiers": [
              "AltGraph"
            ]
          }
        ]
      }
    ],
    "*": [
      {
        "sequence": [
          {
            "key": "Digit8",
            "modifiers": [
              "Shift"
            ]
          }
        ]
      }
    ],
    "°": [
      {
        "sequence": [
          {
            "key": "Digit0",
            "modifiers": [
              "AltGraph"
            ]
          }
        ]
      }
    ],
    "ζ": [
      {
        "sequence": [
          {
            "key": "KeyZ",
            "modifiers": []
          }
        ]
      }
    ],
    "<": [
      {
        "sequence": [
          {
            "key": "Comma",
            "modifiers": [
              "Shift"
            ]
          }
        ]
      },
      {
        "sequence": [
          {
            "key": "IntlBackslash",
            "modifiers": []
          }
        ]
      }
    ],
    "?": [
      {
        "sequence": [
          {
            "key": "Slash",
            "modifiers": [
              "Shift"
            ]
          }
        ]
      }
    ],
    "Κ": [
      {
        "sequence": [
          {
            "key": "KeyK",
            "modifiers": [
              "Shift"
            ]
          }
        ]
      }
    ],
    "!": [
      {
        "sequence": [
          {
            "key": "Digit1",
            "modifiers": [
              "Shift"
            ]
          }
        ]
      }
    ],
    "ο": [
      {
        "sequence": [
          {
            "key": "KeyO",
            "modifiers": []
          }
        ]
      }
    ],
    "σ": [
      {
        "sequence": [
          {
            "key": "KeyS",
            "modifiers": []
          }
        ]
      }
    ],
    "ρ": [
      {
        "sequence": [
          {
            "key": "KeyR",
            "modifiers": []
          }
        ]
      }
    ],
    "³": [
      {
        "sequence": [
          {
            "key": "Digit3",
            "modifiers": [
              "AltGraph"
            ]
          }
        ]
      }
    ],
    "Θ": [
      {
        "sequence": [
          {
            "key": "KeyU",
            "modifiers": [
              "Shift"
            ]
          }
        ]
      }
    ],
    "θ": [
      {
        "sequence": [
          {
            "key": "KeyU",
            "modifiers": []
          }
        ]
      }
    ],
    "ι": [
      {
        "sequence": [
          {
            "key": "KeyI",
            "modifiers": []
          }
        ]
      }
    ],
    "\\": [
      {
        "sequence": [
          {
            "key": "Backslash",
            "modifiers": []
          }
        ]
      }
    ],
    "3": [
      {
        "sequence": [
          {
            "key": "Digit3",
            "modifiers": []
          }
        ]
      }
    ],
    "¥": [
      {
        "sequence": [
          {
            "key": "KeyY",
            "modifiers": [
              "AltGraph"
            ]
          }
        ]
      }
    ],
    "²": [
      {
        "sequence": [
          {
            "key": "Digit2",
            "modifiers": [
              "AltGraph"
            ]
          }
        ]
      }
    ],
    "(": [
      {
        "sequence": [
          {
            "key": "Digit9",
            "modifiers": [
              "Shift"
            ]
          }
        ]
      }
    ],
    "ψ": [
      {
        "sequence": [
          {
            "key": "KeyC",
            "modifiers": []
          }
        ]
      }
    ],
    "Ν": [
      {
        "sequence": [
          {
            "key": "KeyN",
            "modifiers": [
              "Shift"
            ]
          }
        ]
      }
    ],
    "1": [
      {
        "sequence": [
          {
            "key": "Digit1",
            "modifiers": []
          }
        ]
      }
    ],
    "`": [
      {
        "sequence": [
          {
            "key": "Backquote",
            "modifiers": []
          }
        ]
      }
    ],
    "Α": [
      {
        "sequence": [
          {
            "key": "KeyA",
            "modifiers": [
              "Shift"
            ]
          }
        ]
      }
    ],
    "Δ": [
      {
        "sequence": [
          {
            "key": "KeyD",
            "modifiers": [
              "Shift"
            ]
          }
        ]
      }
    ],
    "Σ": [
      {
        "sequence": [
          {
            "key": "KeyS",
            "modifiers": [
              "Shift"
            ]
          }
        ]
      }
    ],
    "Μ": [
      {
        "sequence": [
          {
            "key": "KeyM",
            "modifiers": [
              "Shift"
            ]
          }
        ]
      }
    ],
    "Ζ": [
      {
        "sequence": [
          {
            "key": "KeyZ",
            "modifiers": [
              "Shift"
            ]
          }
        ]
      }
    ],
    "€": [
      {
        "sequence": [
          {
            "key": "KeyE",
            "modifiers": [
              "AltGraph"
            ]
          }
        ]
      }
    ],
    "η": [
      {
        "sequence": [
          {
            "key": "KeyH",
            "modifiers": []
          }
        ]
      }
    ],
    "«": [
      {
        "sequence": [
          {
            "key": "BracketLeft",
            "modifiers": [
              "AltGraph"
            ]
          }
        ]
      }
    ],
    "χ": [
      {
        "sequence": [
          {
            "key": "KeyX",
            "modifiers": []
          }
        ]
      }
    ],
    "τ": [
      {
        "sequence": [
          {
            "key": "KeyT",
            "modifiers": []
          }
        ]
      }
    ],
    "λ": [
      {
        "sequence": [
          {
            "key": "KeyL",
            "modifiers": []
          }
        ]
      }
    ],
    "φ": [
      {
        "sequence": [
          {
            "key": "KeyF",
            "modifiers": []
          }
        ]
      }
    ],
    ":": [
      {
        "sequence": [
          {
            "key": "KeyQ",
            "modifiers": [
              "Shift"
            ]
          }
        ]
      }
    ],
    "Υ": [
      {
        "sequence": [
          {
            "key": "KeyY",
            "modifiers": [
              "Shift"
            ]
          }
        ]
      }
    ],
    "β": [
      {
        "sequence": [
          {
            "key": "KeyB",
            "modifiers": []
          }
        ]
      }
    ],
    "Τ": [
      {
        "sequence": [
          {
            "key": "KeyT",
            "modifiers": [
              "Shift"
            ]
          }
        ]
      }
    ],
    "%": [
      {
        "sequence": [
          {
            "key": "Digit5",
            "modifiers": [
              "Shift"
            ]
          }
        ]
      }
    ],
    "Ι": [
      {
        "sequence": [
          {
            "key": "KeyI",
            "modifiers": [
              "Shift"
            ]
          }
        ]
      }
    ],
    "^": [
      {
        "sequence": [
          {
            "key": "Digit6",
            "modifiers": [
              "Shift"
            ]
          }
        ]
      }
    ],
    "®": [
      {
        "sequence": [
          {
            "key": "KeyR",
            "modifiers": [
              "AltGraph"
            ]
          }
        ]
      }
    ],
    "δ": [
      {
        "sequence": [
          {
            "key": "KeyD",
            "modifiers": []
          }
        ]
      }
    ],
    "4": [
      {
        "sequence": [
          {
            "key": "Digit4",
            "modifiers": []
          }
        ]
      }
    ],
    "Ρ": [
      {
        "sequence": [
          {
            "key": "KeyR",
            "modifiers": [
              "Shift"
            ]
          }
        ]
      }
    ],
    "]": [
      {
        "sequence": [
          {
            "key": "BracketRight",
            "modifiers": []
          }
        ]
      }
    ],
    "υ": [
      {
        "sequence": [
          {
            "key": "KeyY",
            "modifiers": []
          }
        ]
      }
    ],
    "κ": [
      {
        "sequence": [
          {
            "key": "KeyK",
            "modifiers": []
          }
        ]
      }
    ],
    "¬": [
      {
        "sequence": [
          {
            "key": "Backslash",
            "modifiers": [
              "AltGraph"
            ]
          }
        ]
      }
    ],
    "0": [
      {
        "sequence": [
          {
            "key": "Digit0",
            "modifiers": []
          }
        ]
      }
    ],
    "#": [
      {
        "sequence": [
          {
            "key": "Digit3",
            "modifiers": [
              "Shift"
            ]
          }
        ]
      }
    ],
    "Β": [
      {
        "sequence": [
          {
            "key": "KeyB",
            "modifiers": [
              "Shift"
            ]
          }
        ]
      }
    ],
    ",": [
      {
        "sequence": [
          {
            "key": "Comma",
            "modifiers": []
          }
        ]
      }
    ],
    "ξ": [
      {
        "sequence": [
          {
            "key": "KeyJ",
            "modifiers": []
          }
        ]
      }
    ],
    "Ω": [
      {
        "sequence": [
          {
            "key": "KeyV",
            "modifiers": [
              "Shift"
            ]
          }
        ]
      }
    ],
    "[": [
      {
        "sequence": [
          {
            "key": "BracketLeft",
            "modifiers": []
          }
        ]
      }
    ],
    ".": [
      {
        "sequence": [
          {
            "key": "Period",
            "modifiers": []
          }
        ]
      }
    ],
    "@": [
      {
        "sequence": [
          {
            "key": "Digit2",
            "modifiers": [
              "Shift"
            ]
          }
        ]
      }
    ],
    "γ": [
      {
        "sequence": [
          {
            "key": "KeyG",
            "modifiers": []
          }
        ]
      }
    ],
    ">": [
      {
        "sequence": [
          {
            "key": "Period",
            "modifiers": [
              "Shift"
            ]
          }
        ]
      },
      {
        "sequence": [
          {
            "key": "IntlBackslash",
            "modifiers": [
              "Shift"
            ]
          }
        ]
      }
    ],
    " ": [
      {
        "sequence": [
          {
            "key": "Space",
            "modifiers": []
          }
        ]
      },
      {
        "sequence": [
          {
            "key": "Space",
            "modifiers": [
              "Shift"
            ]
          }
        ]
      }
    ],
    "5": [
      {
        "sequence": [
          {
            "key": "Digit5",
            "modifiers": []
          }
        ]
      }
    ],
    "~": [
      {
        "sequence": [
          {
            "key": "Backquote",
            "modifiers": [
              "Shift"
            ]
          }
        ]
      }
    ],
    "¶": [
      {
        "sequence": [
          {
            "key": "Digit6",
            "modifiers": [
              "AltGraph"
            ]
          }
        ]
      }
    ],
    "Ο": [
      {
        "sequence": [
          {
            "key": "KeyO",
            "modifiers": [
              "Shift"
            ]
          }
        ]
      }
    ],
    "Η": [
      {
        "sequence": [
          {
            "key": "KeyH",
            "modifiers": [
              "Shift"
            ]
          }
        ]
      }
    ],
    "Π": [
      {
        "sequence": [
          {
            "key": "KeyP",
            "modifiers": [
              "Shift"
            ]
          }
        ]
      }
    ],
    "μ": [
      {
        "sequence": [
          {
            "key": "KeyM",
            "modifiers": []
          }
        ]
      }
    ],
    "6": [
      {
        "sequence": [
          {
            "key": "Digit6",
            "modifiers": []
          }
        ]
      }
    ]
  }
}