{
  "metadata": {
    "platform": "windows",
    "layout_name": "00020426",
    "display_name": "Latvian (Standard)",
    "extracted_on": "2026-07-07T00:41:46Z"
  },
  "mappings": {
    "Q": [
      {
        "sequence": [
          {
            "key": "KeyQ",
            "modifiers": [
              "Shift"
            ]
          }
        ]
      }
    ],
    "Ē": [
      {
        "sequence": [
          {
            "key": "KeyE",
            "modifiers": [
              "Shift",
              "AltGraph"
            ]
          }
        ]
      }
    ],
    "L": [
      {
        "sequence": [
          {
            "key": "KeyL",
            "modifiers": [
              "Shift"
            ]
          }
        ]
      }
    ],
    "7": [
      {
        "sequence": [
          {
            "key": "Digit7",
            "modifiers": []
          }
        ]
      }
    ],
    "K": [
      {
        "sequence": [
          {
            "key": "KeyK",
            "modifiers": [
              "Shift"
            ]
          }
        ]
      }
    ],
    "!": [
      {
        "sequence": [
          {
            "key": "Digit1",
            "modifiers": [
              "Shift"
            ]
          }
        ]
      }
    ],
    "Ķ": [
      {
        "sequence": [
          {
            "key": "KeyK",
            "modifiers": [
              "Shift",
              "AltGraph"
            ]
          }
        ]
      }
    ],
    "B": [
      {
        "sequence": [
          {
            "key": "KeyB",
            "modifiers": [
              "Shift"
            ]
          }
        ]
      }
    ],
    " ": [
      {
        "sequence": [
          {
            "key": "Space",
            "modifiers": []
          }
        ]
      },
      {
        "sequence": [
          {
            "key": "Space",
            "modifiers": [
              "Shift"
            ]
          }
        ]
      }
    ],
    "I": [
      {
        "sequence": [
          {
            "key": "KeyI",
            "modifiers": [
              "Shift"
            ]
          }
        ]
      }
    ],
    "X": [
      {
        "sequence": [
          {
            "key": "KeyX",
            "modifiers": [
              "Shift"
            ]
          }
        ]
      }
    ],
    "p": [
      {
        "sequence": [
          {
            "key": "KeyP",
            "modifiers": []
          }
        ]
      }
    ],
    "0": [
      {
        "sequence": [
          {
            "key": "Digit0",
            "modifiers": []
          }
        ]
      }
    ],
    "š": [
      {
        "sequence": [
          {
            "key": "KeyS",
            "modifiers": [
              "AltGraph"
            ]
          }
        ]
      }
    ],
    "d": [
      {
        "sequence": [
          {
            "key": "KeyD",
            "modifiers": []
          }
        ]
      }
    ],
    "x": [
      {
        "sequence": [
          {
            "key": "KeyX",
            "modifiers": []
          }
        ]
      }
    ],
    "c": [
      {
        "sequence": [
          {
            "key": "KeyC",
            "modifiers": []
          }
        ]
      }
    ],
    "4": [
      {
        "sequence": [
          {
            "key": "Digit4",
            "modifiers": []
          }
        ]
      }
    ],
    "R": [
      {
        "sequence": [
          {
            "key": "KeyR",
            "modifiers": [
              "Shift"
            ]
          }
        ]
      }
    ],
    "@": [
      {
        "sequence": [
          {
            "key": "Digit2",
            "modifiers": [
              "Shift"
            ]
          }
        ]
      }
    ],
    "5": [
      {
        "sequence": [
          {
            "key": "Digit5",
            "modifiers": []
          }
        ]
      }
    ],
    "~": [
      {
        "sequence": [
          {
            "key": "Backquote",
            "modifiers": [
              "Shift"
            ]
          }
        ]
      }
    ],
    "=": [
      {
        "sequence": [
          {
            "key": "Equal",
            "modifiers": []
          }
        ]
      }
    ],
    "N": [
      {
        "sequence": [
          {
            "key": "KeyN",
            "modifiers": [
              "Shift"
            ]
          }
        ]
      }
    ],
    "Ņ": [
      {
        "sequence": [
          {
            "key": "KeyN",
            "modifiers": [
              "Shift",
              "AltGraph"
            ]
          }
        ]
      }
    ],
    "ņ": [
      {
        "sequence": [
          {
            "key": "KeyN",
            "modifiers": [
              "AltGraph"
            ]
          }
        ]
      }
    ],
    "—": [
      {
        "sequence": [
          {
            "key": "Minus",
            "modifiers": [
              "Shift",
              "AltGraph"
            ]
          }
        ]
      }
    ],
    "g": [
      {
        "sequence": [
          {
            "key": "KeyG",
            "modifiers": []
          }
        ]
      }
    ],
    "6": [
      {
        "sequence": [
          {
            "key": "Digit6",
            "modifiers": []
          }
        ]
      }
    ],
    "ī": [
      {
        "sequence": [
          {
            "key": "KeyI",
            "modifiers": [
              "AltGraph"
            ]
          }
        ]
      }
    ],
    ";": [
      {
        "sequence": [
          {
            "key": "Semicolon",
            "modifiers": []
          }
        ]
      }
    ],
    "/": [
      {
        "sequence": [
          {
            "key": "Slash",
            "modifiers": []
          }
        ]
      }
    ],
    "€": [
      {
        "sequence": [
          {
            "key": "Digit4",
            "modifiers": [
              "AltGraph"
            ]
          }
        ]
      }
    ],
    ".": [
      {
        "sequence": [
          {
            "key": "Period",
            "modifiers": []
          }
        ]
      }
    ],
    "Ŗ": [
      {
        "sequence": [
          {
            "key": "KeyR",
            "modifiers": [
              "Shift",
              "AltGraph"
            ]
          }
        ]
      }
    ],
    "8": [
      {
        "sequence": [
          {
            "key": "Digit8",
            "modifiers": []
          }
        ]
      }
    ],
    "(": [
      {
        "sequence": [
          {
            "key": "Digit9",
            "modifiers": [
              "Shift"
            ]
          }
        ]
      }
    ],
    "9": [
      {
        "sequence": [
          {
            "key": "Digit9",
            "modifiers": []
          }
        ]
      }
    ],
    "z": [
      {
        "sequence": [
          {
            "key": "KeyZ",
            "modifiers": []
          }
        ]
      }
    ],
    "2": [
      {
        "sequence": [
          {
            "key": "Digit2",
            "modifiers": []
          }
        ]
      }
    ],
    "*": [
      {
        "sequence": [
          {
            "key": "Digit8",
            "modifiers": [
              "Shift"
            ]
          }
        ]
      }
    ],
    "v": [
      {
        "sequence": [
          {
            "key": "KeyV",
            "modifiers": []
          }
        ]
      }
    ],
    "\\": [
      {
        "sequence": [
          {
            "key": "Backslash",
            "modifiers": []
          }
        ]
      },
      {
        "sequence": [
          {
            "key": "IntlBackslash",
            "modifiers": []
          }
        ]
      }
    ],
    "e": [
      {
        "sequence": [
          {
            "key": "KeyE",
            "modifiers": []
          }
        ]
      }
    ],
    "{": [
      {
        "sequence": [
          {
            "key": "BracketLeft",
            "modifiers": [
              "Shift"
            ]
          }
        ]
      }
    ],
    "Š": [
      {
        "sequence": [
          {
            "key": "KeyS",
            "modifiers": [
              "Shift",
              "AltGraph"
            ]
          }
        ]
      }
    ],
    "w": [
      {
        "sequence": [
          {
            "key": "KeyW",
            "modifiers": []
          }
        ]
      }
    ],
    ":": [
      {
        "sequence": [
          {
            "key": "Semicolon",
            "modifiers": [
              "Shift"
            ]
          }
        ]
      }
    ],
    "s": [
      {
        "sequence": [
          {
            "key": "KeyS",
            "modifiers": []
          }
        ]
      }
    ],
    "Ū": [
      {
        "sequence": [
          {
            "key": "KeyU",
            "modifiers": [
              "Shift",
              "AltGraph"
            ]
          }
        ]
      }
    ],
    "­": [
      {
        "sequence": [
          {
            "key": "Backquote",
            "modifiers": [
              "AltGraph"
            ]
          }
        ]
      }
    ],
    " ": [
      {
        "sequence": [
          {
            "key": "Digit1",
            "modifiers": [
              "AltGraph"
            ]
          }
        ]
      }
    ],
    "Y": [
      {
        "sequence": [
          {
            "key": "KeyY",
            "modifiers": [
              "Shift"
            ]
          }
        ]
      }
    ],
    "H": [
      {
        "sequence": [
          {
            "key": "KeyH",
            "modifiers": [
              "Shift"
            ]
          }
        ]
      }
    ],
    "y": [
      {
        "sequence": [
          {
            "key": "KeyY",
            "modifiers": []
          }
        ]
      }
    ],
    "×": [
      {
        "sequence": [
          {
            "key": "Digit8",
            "modifiers": [
              "Shift",
              "AltGraph"
            ]
          }
        ]
      }
    ],
    "f": [
      {
        "sequence": [
          {
            "key": "KeyF",
            "modifiers": []
          }
        ]
      }
    ],
    "Ģ": [
      {
        "sequence": [
          {
            "key": "KeyG",
            "modifiers": [
              "Shift",
              "AltGraph"
            ]
          }
        ]
      }
    ],
    "J": [
      {
        "sequence": [
          {
            "key": "KeyJ",
            "modifiers": [
              "Shift"
            ]
          }
        ]
      }
    ],
    ">": [
      {
        "sequence": [
          {
            "key": "Period",
            "modifiers": [
              "Shift"
            ]
          }
        ]
      }
    ],
    "ō": [
      {
        "sequence": [
          {
            "key": "KeyO",
            "modifiers": [
              "AltGraph"
            ]
          }
        ]
      }
    ],
    "S": [
      {
        "sequence": [
          {
            "key": "KeyS",
            "modifiers": [
              "Shift"
            ]
          }
        ]
      }
    ],
    "Č": [
      {
        "sequence": [
          {
            "key": "KeyC",
            "modifiers": [
              "Shift",
              "AltGraph"
            ]
          }
        ]
      }
    ],
    "C": [
      {
        "sequence": [
          {
            "key": "KeyC",
            "modifiers": [
              "Shift"
            ]
          }
        ]
      }
    ],
    "&": [
      {
        "sequence": [
          {
            "key": "Digit7",
            "modifiers": [
              "Shift"
            ]
          }
        ]
      }
    ],
    "l": [
      {
        "sequence": [
          {
            "key": "KeyL",
            "modifiers": []
          }
        ]
      }
    ],
    "}": [
      {
        "sequence": [
          {
            "key": "BracketRight",
            "modifiers": [
              "Shift"
            ]
          }
        ]
      }
    ],
    "ē": [
      {
        "sequence": [
          {
            "key": "KeyE",
            "modifiers": [
              "AltGraph"
            ]
          }
        ]
      }
    ],
    "V": [
      {
        "sequence": [
          {
            "key": "KeyV",
            "modifiers": [
              "Shift"
            ]
          }
        ]
      }
    ],
    "m": [
      {
        "sequence": [
          {
            "key": "KeyM",
            "modifiers": []
          }
        ]
      }
    ],
    "’": [
      {
        "sequence": [
          {
            "key": "Digit6",
            "modifiers": [
              "AltGraph"
            ]
          }
        ]
      }
    ],
    ")": [
      {
        "sequence": [
          {
            "key": "Digit0",
            "modifiers": [
              "Shift"
            ]
          }
        ]
      }
    ],
    "Z": [
      {
        "sequence": [
          {
            "key": "KeyZ",
            "modifiers": [
              "Shift"
            ]
          }
        ]
      }
    ],
    "?": [
      {
        "sequence": [
          {
            "key": "Slash",
            "modifiers": [
              "Shift"
            ]
          }
        ]
      }
    ],
    "Ž": [
      {
        "sequence": [
          {
            "key": "KeyZ",
            "modifiers": [
              "Shift",
              "AltGraph"
            ]
          }
        ]
      }
    ],
    "ķ": [
      {
        "sequence": [
          {
            "key": "KeyK",
            "modifiers": [
              "AltGraph"
            ]
          }
        ]
      }
    ],
    "M": [
      {
        "sequence": [
          {
            "key": "KeyM",
            "modifiers": [
              "Shift"
            ]
          }
        ]
      }
    ],
    "-": [
      {
        "sequence": [
          {
            "key": "Minus",
            "modifiers": []
          }
        ]
      }
    ],
    "Ā": [
      {
        "sequence": [
          {
            "key": "KeyA",
            "modifiers": [
              "Shift",
              "AltGraph"
            ]
          }
        ]
      }
    ],
    "E": [
      {
        "sequence": [
          {
            "key": "KeyE",
            "modifiers": [
              "Shift"
            ]
          }
        ]
      }
    ],
    "P": [
      {
        "sequence": [
          {
            "key": "KeyP",
            "modifiers": [
              "Shift"
            ]
          }
        ]
      }
    ],
    "»": [
      {
        "sequence": [
          {
            "key": "Digit3",
            "modifiers": [
              "AltGraph"
            ]
          }
        ]
      }
    ],
    "u": [
      {
        "sequence": [
          {
            "key": "KeyU",
            "modifiers": []
          }
        ]
      }
    ],
    "F": [
      {
        "sequence": [
          {
            "key": "KeyF",
            "modifiers": [
              "Shift"
            ]
          }
        ]
      }
    ],
    "ģ": [
      {
        "sequence": [
          {
            "key": "KeyG",
            "modifiers": [
              "AltGraph"
            ]
          }
        ]
      }
    ],
    "G": [
      {
        "sequence": [
          {
            "key": "KeyG",
            "modifiers": [
              "Shift"
            ]
          }
        ]
      }
    ],
    "h": [
      {
        "sequence": [
          {
            "key": "KeyH",
            "modifiers": []
          }
        ]
      }
    ],
    "<": [
      {
        "sequence": [
          {
            "key": "Comma",
            "modifiers": [
              "Shift"
            ]
          }
        ]
      }
    ],
    "«": [
      {
        "sequence": [
          {
            "key": "Digit2",
            "modifiers": [
              "AltGraph"
            ]
          }
        ]
      }
    ],
    "1": [
      {
        "sequence": [
          {
            "key": "Digit1",
            "modifiers": []
          }
        ]
      }
    ],
    "|": [
      {
        "sequence": [
          {
            "key": "Backslash",
            "modifiers": [
              "Shift"
            ]
          }
        ]
      },
      {
        "sequence": [
          {
            "key": "IntlBackslash",
            "modifiers": [
              "Shift"
            ]
          }
        ]
      }
    ],
    "%": [
      {
        "sequence": [
          {
            "key": "Digit5",
            "modifiers": [
              "Shift"
            ]
          }
        ]
      }
    ],
    "ž": [
      {
        "sequence": [
          {
            "key": "KeyZ",
            "modifiers": [
              "AltGraph"
            ]
          }
        ]
      }
    ],
    "D": [
      {
        "sequence": [
          {
            "key": "KeyD",
            "modifiers": [
              "Shift"
            ]
          }
        ]
      }
    ],
    "T": [
      {
        "sequence": [
          {
            "key": "KeyT",
            "modifiers": [
              "Shift"
            ]
          }
        ]
      }
    ],
    "O": [
      {
        "sequence": [
          {
            "key": "KeyO",
            "modifiers": [
              "Shift"
            ]
          }
        ]
      }
    ],
    "[": [
      {
        "sequence": [
          {
            "key": "BracketLeft",
            "modifiers": []
          }
        ]
      }
    ],
    "ā": [
      {
        "sequence": [
          {
            "key": "KeyA",
            "modifiers": [
              "AltGraph"
            ]
          }
        ]
      }
    ],
    "§": [
      {
        "sequence": [
          {
            "key": "Digit4",
            "modifiers": [
              "Shift",
              "AltGraph"
            ]
          }
        ]
      }
    ],
    "r": [
      {
        "sequence": [
          {
            "key": "KeyR",
            "modifiers": []
          }
        ]
      }
    ],
    "Ō": [
      {
        "sequence": [
          {
            "key": "KeyO",
            "modifiers": [
              "Shift",
              "AltGraph"
            ]
          }
        ]
      }
    ],
    "q": [
      {
        "sequence": [
          {
            "key": "KeyQ",
            "modifiers": []
          }
        ]
      }
    ],
    "ļ": [
      {
        "sequence": [
          {
            "key": "KeyL",
            "modifiers": [
              "AltGraph"
            ]
          }
        ]
      }
    ],
    "^": [
      {
        "sequence": [
          {
            "key": "Digit6",
            "modifiers": [
              "Shift"
            ]
          }
        ]
      }
    ],
    "b": [
      {
        "sequence": [
          {
            "key": "KeyB",
            "modifiers": []
          }
        ]
      }
    ],
    "i": [
      {
        "sequence": [
          {
            "key": "KeyI",
            "modifiers": []
          }
        ]
      }
    ],
    ",": [
      {
        "sequence": [
          {
            "key": "Comma",
            "modifiers": []
          }
        ]
      }
    ],
    "#": [
      {
        "sequence": [
          {
            "key": "Digit3",
            "modifiers": [
              "Shift"
            ]
          }
        ]
      }
    ],
    "_": [
      {
        "sequence": [
          {
            "key": "Minus",
            "modifiers": [
              "Shift"
            ]
          }
        ]
      }
    ],
    "]": [
      {
        "sequence": [
          {
            "key": "BracketRight",
            "modifiers": []
          }
        ]
      }
    ],
    "č": [
      {
        "sequence": [
          {
            "key": "KeyC",
            "modifiers": [
              "AltGraph"
            ]
          }
        ]
      }
    ],
    "3": [
      {
        "sequence": [
          {
            "key": "Digit3",
            "modifiers": []
          }
        ]
      }
    ],
    "Ī": [
      {
        "sequence": [
          {
            "key": "KeyI",
            "modifiers": [
              "Shift",
              "AltGraph"
            ]
          }
        ]
      }
    ],
    "n": [
      {
        "sequence": [
          {
            "key": "KeyN",
            "modifiers": []
          }
        ]
      }
    ],
    "ŗ": [
      {
        "sequence": [
          {
            "key": "KeyR",
            "modifiers": [
              "AltGraph"
            ]
          }
        ]
      }
    ],
    "$": [
      {
        "sequence": [
          {
            "key": "Digit4",
            "modifiers": [
              "Shift"
            ]
          }
        ]
      }
    ],
    "°": [
      {
        "sequence": [
          {
            "key": "Digit5",
            "modifiers": [
              "Shift",
              "AltGraph"
            ]
          }
        ]
      }
    ],
    "a": [
      {
        "sequence": [
          {
            "key": "KeyA",
            "modifiers": []
          }
        ]
      }
    ],
    "W": [
      {
        "sequence": [
          {
            "key": "KeyW",
            "modifiers": [
              "Shift"
            ]
          }
        ]
      }
    ],
    "±": [
      {
        "sequence": [
          {
            "key": "Digit7",
            "modifiers": [
              "Shift",
              "AltGraph"
            ]
          }
        ]
      }
    ],
    "t": [
      {
        "sequence": [
          {
            "key": "KeyT",
            "modifiers": []
          }
        ]
      }
    ],
    "o": [
      {
        "sequence": [
          {
            "key": "KeyO",
            "modifiers": []
          }
        ]
      }
    ],
    "`": [
      {
        "sequence": [
          {
            "key": "Backquote",
            "modifiers": []
          }
        ]
      }
    ],
    "A": [
      {
        "sequence": [
          {
            "key": "KeyA",
            "modifiers": [
              "Shift"
            ]
          }
        ]
      }
    ],
    "–": [
      {
        "sequence": [
          {
            "key": "Minus",
            "modifiers": [
              "AltGraph"
            ]
          }
        ]
      }
    ],
    "+": [
      {
        "sequence": [
          {
            "key": "Equal",
            "modifiers": [
              "Shift"
            ]
          }
        ]
      }
    ],
    "k": [
      {
        "sequence": [
          {
            "key": "KeyK",
            "modifiers": []
          }
        ]
      }
    ],
    "U": [
      {
        "sequence": [
          {
            "key": "KeyU",
            "modifiers": [
              "Shift"
            ]
          }
        ]
      }
    ],
    "j": [
      {
        "sequence": [
          {
            "key": "KeyJ",
            "modifiers": []
          }
        ]
      }
    ],
    "ū": [
      {
        "sequence": [
          {
            "key": "KeyU",
            "modifiers": [
              "AltGraph"
            ]
          }
        ]
      }
    ],
    "Ļ": [
      {
        "sequence": [
          {
            "key": "KeyL",
            "modifiers": [
              "Shift",
              "AltGraph"
            ]
          }
        ]
      }
    ]
  }
}