{
  "metadata": {
    "platform": "linux",
    "layout_name": "fr",
    "layout_variant": "oss_nodeadkeys",
    "display_name": "French (alt., no dead keys)",
    "extracted_on": "2026-07-07T01:15:29Z"
  },
  "mappings": {
    "È": [
      {
        "sequence": [
          {
            "key": "Digit7",
            "modifiers": [
              "Shift",
              "AltGraph"
            ]
          }
        ]
      }
    ],
    "Q": [
      {
        "sequence": [
          {
            "key": "KeyA",
            "modifiers": [
              "Shift"
            ]
          }
        ]
      }
    ],
    "D": [
      {
        "sequence": [
          {
            "key": "KeyD",
            "modifiers": [
              "Shift"
            ]
          }
        ]
      }
    ],
    "³": [
      {
        "sequence": [
          {
            "key": "Backquote",
            "modifiers": [
              "Shift"
            ]
          }
        ]
      }
    ],
    "î": [
      {
        "sequence": [
          {
            "key": "KeyI",
            "modifiers": [
              "AltGraph"
            ]
          }
        ]
      }
    ],
    "|": [
      {
        "sequence": [
          {
            "key": "Digit6",
            "modifiers": [
              "AltGraph"
            ]
          }
        ]
      }
    ],
    "’": [
      {
        "sequence": [
          {
            "key": "KeyG",
            "modifiers": [
              "AltGraph"
            ]
          }
        ]
      }
    ],
    "O": [
      {
        "sequence": [
          {
            "key": "KeyO",
            "modifiers": [
              "Shift"
            ]
          }
        ]
      }
    ],
    "Å": [
      {
        "sequence": [
          {
            "key": "BracketLeft",
            "modifiers": [
              "Shift",
              "AltGraph"
            ]
          }
        ]
      }
    ],
    "ð": [
      {
        "sequence": [
          {
            "key": "KeyH",
            "modifiers": [
              "AltGraph"
            ]
          }
        ]
      }
    ],
    "Ŀ": [
      {
        "sequence": [
          {
            "key": "KeyL",
            "modifiers": [
              "Shift",
              "AltGraph"
            ]
          }
        ]
      }
    ],
    "i": [
      {
        "sequence": [
          {
            "key": "KeyI",
            "modifiers": []
          }
        ]
      }
    ],
    "x": [
      {
        "sequence": [
          {
            "key": "KeyX",
            "modifiers": []
          }
        ]
      }
    ],
    "_": [
      {
        "sequence": [
          {
            "key": "Digit8",
            "modifiers": []
          }
        ]
      }
    ],
    "Æ": [
      {
        "sequence": [
          {
            "key": "KeyQ",
            "modifiers": [
              "Shift",
              "AltGraph"
            ]
          }
        ]
      }
    ],
    "c": [
      {
        "sequence": [
          {
            "key": "KeyC",
            "modifiers": []
          }
        ]
      }
    ],
    "®": [
      {
        "sequence": [
          {
            "key": "KeyC",
            "modifiers": [
              "Shift",
              "AltGraph"
            ]
          }
        ]
      }
    ],
    "ŀ": [
      {
        "sequence": [
          {
            "key": "KeyL",
            "modifiers": [
              "AltGraph"
            ]
          }
        ]
      }
    ],
    " ": [
      {
        "sequence": [
          {
            "key": "KeyV",
            "modifiers": [
              "AltGraph"
            ]
          }
        ]
      }
    ],
    "b": [
      {
        "sequence": [
          {
            "key": "KeyB",
            "modifiers": []
          }
        ]
      }
    ],
    "n": [
      {
        "sequence": [
          {
            "key": "KeyN",
            "modifiers": []
          }
        ]
      }
    ],
    "(": [
      {
        "sequence": [
          {
            "key": "Digit5",
            "modifiers": []
          }
        ]
      }
    ],
    "s": [
      {
        "sequence": [
          {
            "key": "KeyS",
            "modifiers": []
          }
        ]
      }
    ],
    ":": [
      {
        "sequence": [
          {
            "key": "Period",
            "modifiers": []
          }
        ]
      }
    ],
    "æ": [
      {
        "sequence": [
          {
            "key": "KeyQ",
            "modifiers": [
              "AltGraph"
            ]
          }
        ]
      }
    ],
    "\\": [
      {
        "sequence": [
          {
            "key": "Digit8",
            "modifiers": [
              "AltGraph"
            ]
          }
        ]
      }
    ],
    "a": [
      {
        "sequence": [
          {
            "key": "KeyQ",
            "modifiers": []
          }
        ]
      }
    ],
    " ": [
      {
        "sequence": [
          {
            "key": "Space",
            "modifiers": []
          }
        ]
      },
      {
        "sequence": [
          {
            "key": "Space",
            "modifiers": [
              "Shift"
            ]
          }
        ]
      },
      {
        "sequence": [
          {
            "key": "Space",
            "modifiers": [
              "AltGraph"
            ]
          }
        ]
      }
    ],
    "—": [
      {
        "sequence": [
          {
            "key": "Digit4",
            "modifiers": [
              "Shift",
              "AltGraph"
            ]
          }
        ]
      }
    ],
    "g": [
      {
        "sequence": [
          {
            "key": "KeyG",
            "modifiers": []
          }
        ]
      }
    ],
    "˛": [
      {
        "sequence": [
          {
            "key": "Digit1",
            "modifiers": [
              "Shift",
              "AltGraph"
            ]
          }
        ]
      }
    ],
    "¥": [
      {
        "sequence": [
          {
            "key": "KeyG",
            "modifiers": [
              "Shift",
              "AltGraph"
            ]
          }
        ]
      }
    ],
    "∕": [
      {
        "sequence": [
          {
            "key": "Period",
            "modifiers": [
              "Shift",
              "AltGraph"
            ]
          }
        ]
      }
    ],
    "!": [
      {
        "sequence": [
          {
            "key": "Slash",
            "modifiers": []
          }
        ]
      }
    ],
    "¡": [
      {
        "sequence": [
          {
            "key": "Slash",
            "modifiers": [
              "AltGraph"
            ]
          }
        ]
      }
    ],
    ">": [
      {
        "sequence": [
          {
            "key": "IntlBackslash",
            "modifiers": [
              "Shift"
            ]
          }
        ]
      }
    ],
    "²": [
      {
        "sequence": [
          {
            "key": "Backquote",
            "modifiers": []
          }
        ]
      }
    ],
    "÷": [
      {
        "sequence": [
          {
            "key": "Period",
            "modifiers": [
              "AltGraph"
            ]
          }
        ]
      }
    ],
    "Ë": [
      {
        "sequence": [
          {
            "key": "KeyD",
            "modifiers": [
              "Shift",
              "AltGraph"
            ]
          }
        ]
      }
    ],
    "4": [
      {
        "sequence": [
          {
            "key": "Digit4",
            "modifiers": [
              "Shift"
            ]
          }
        ]
      }
    ],
    "ï": [
      {
        "sequence": [
          {
            "key": "KeyK",
            "modifiers": [
              "AltGraph"
            ]
          }
        ]
      }
    ],
    ".": [
      {
        "sequence": [
          {
            "key": "Comma",
            "modifiers": [
              "Shift"
            ]
          }
        ]
      }
    ],
    "h": [
      {
        "sequence": [
          {
            "key": "KeyH",
            "modifiers": []
          }
        ]
      }
    ],
    "z": [
      {
        "sequence": [
          {
            "key": "KeyW",
            "modifiers": []
          }
        ]
      }
    ],
    "â": [
      {
        "sequence": [
          {
            "key": "KeyW",
            "modifiers": [
              "AltGraph"
            ]
          }
        ]
      }
    ],
    "ô": [
      {
        "sequence": [
          {
            "key": "KeyP",
            "modifiers": [
              "AltGraph"
            ]
          }
        ]
      }
    ],
    "G": [
      {
        "sequence": [
          {
            "key": "KeyG",
            "modifiers": [
              "Shift"
            ]
          }
        ]
      }
    ],
    "X": [
      {
        "sequence": [
          {
            "key": "KeyX",
            "modifiers": [
              "Shift"
            ]
          }
        ]
      }
    ],
    "ˇ": [
      {
        "sequence": [
          {
            "key": "Digit1",
            "modifiers": [
              "AltGraph"
            ]
          }
        ]
      }
    ],
    "Þ": [
      {
        "sequence": [
          {
            "key": "KeyT",
            "modifiers": [
              "Shift",
              "AltGraph"
            ]
          }
        ]
      }
    ],
    "±": [
      {
        "sequence": [
          {
            "key": "Equal",
            "modifiers": [
              "Shift",
              "AltGraph"
            ]
          }
        ]
      }
    ],
    "«": [
      {
        "sequence": [
          {
            "key": "KeyZ",
            "modifiers": [
              "AltGraph"
            ]
          }
        ]
      }
    ],
    "k": [
      {
        "sequence": [
          {
            "key": "KeyK",
            "modifiers": []
          }
        ]
      }
    ],
    "T": [
      {
        "sequence": [
          {
            "key": "KeyT",
            "modifiers": [
              "Shift"
            ]
          }
        ]
      }
    ],
    "I": [
      {
        "sequence": [
          {
            "key": "KeyI",
            "modifiers": [
              "Shift"
            ]
          }
        ]
      }
    ],
    "–": [
      {
        "sequence": [
          {
            "key": "Digit5",
            "modifiers": [
              "Shift",
              "AltGraph"
            ]
          }
        ]
      }
    ],
    "W": [
      {
        "sequence": [
          {
            "key": "KeyZ",
            "modifiers": [
              "Shift"
            ]
          }
        ]
      }
    ],
    "ø": [
      {
        "sequence": [
          {
            "key": "BracketRight",
            "modifiers": [
              "AltGraph"
            ]
          }
        ]
      }
    ],
    "`": [
      {
        "sequence": [
          {
            "key": "Digit7",
            "modifiers": [
              "AltGraph"
            ]
          }
        ]
      },
      {
        "sequence": [
          {
            "key": "Backslash",
            "modifiers": [
              "AltGraph"
            ]
          }
        ]
      }
    ],
    "”": [
      {
        "sequence": [
          {
            "key": "KeyX",
            "modifiers": [
              "Shift",
              "AltGraph"
            ]
          }
        ]
      }
    ],
    "^": [
      {
        "sequence": [
          {
            "key": "Digit9",
            "modifiers": [
              "AltGraph"
            ]
          }
        ]
      },
      {
        "sequence": [
          {
            "key": "BracketLeft",
            "modifiers": []
          }
        ]
      }
    ],
    "≠": [
      {
        "sequence": [
          {
            "key": "Minus",
            "modifiers": [
              "Shift",
              "AltGraph"
            ]
          }
        ]
      }
    ],
    "p": [
      {
        "sequence": [
          {
            "key": "KeyP",
            "modifiers": []
          }
        ]
      }
    ],
    "o": [
      {
        "sequence": [
          {
            "key": "KeyO",
            "modifiers": []
          }
        ]
      }
    ],
    "$": [
      {
        "sequence": [
          {
            "key": "BracketRight",
            "modifiers": []
          }
        ]
      }
    ],
    "f": [
      {
        "sequence": [
          {
            "key": "KeyF",
            "modifiers": []
          }
        ]
      }
    ],
    "ÿ": [
      {
        "sequence": [
          {
            "key": "KeyY",
            "modifiers": [
              "AltGraph"
            ]
          }
        ]
      }
    ],
    "©": [
      {
        "sequence": [
          {
            "key": "KeyC",
            "modifiers": [
              "AltGraph"
            ]
          }
        ]
      }
    ],
    "™": [
      {
        "sequence": [
          {
            "key": "Digit8",
            "modifiers": [
              "Shift",
              "AltGraph"
            ]
          }
        ]
      }
    ],
    "¨": [
      {
        "sequence": [
          {
            "key": "BracketLeft",
            "modifiers": [
              "Shift"
            ]
          }
        ]
      }
    ],
    "B": [
      {
        "sequence": [
          {
            "key": "KeyB",
            "modifiers": [
              "Shift"
            ]
          }
        ]
      }
    ],
    "¿": [
      {
        "sequence": [
          {
            "key": "KeyM",
            "modifiers": [
              "AltGraph"
            ]
          }
        ]
      }
    ],
    "Û": [
      {
        "sequence": [
          {
            "key": "KeyU",
            "modifiers": [
              "Shift",
              "AltGraph"
            ]
          }
        ]
      }
    ],
    "Ê": [
      {
        "sequence": [
          {
            "key": "KeyR",
            "modifiers": [
              "Shift",
              "AltGraph"
            ]
          }
        ]
      }
    ],
    "≥": [
      {
        "sequence": [
          {
            "key": "IntlBackslash",
            "modifiers": [
              "Shift",
              "AltGraph"
            ]
          }
        ]
      }
    ],
    "-": [
      {
        "sequence": [
          {
            "key": "Digit6",
            "modifiers": []
          }
        ]
      }
    ],
    "ö": [
      {
        "sequence": [
          {
            "key": "Semicolon",
            "modifiers": [
              "AltGraph"
            ]
          }
        ]
      }
    ],
    "è": [
      {
        "sequence": [
          {
            "key": "Digit7",
            "modifiers": []
          }
        ]
      }
    ],
    "û": [
      {
        "sequence": [
          {
            "key": "KeyU",
            "modifiers": [
              "AltGraph"
            ]
          }
        ]
      }
    ],
    "Ÿ": [
      {
        "sequence": [
          {
            "key": "KeyY",
            "modifiers": [
              "Shift",
              "AltGraph"
            ]
          }
        ]
      }
    ],
    "N": [
      {
        "sequence": [
          {
            "key": "KeyN",
            "modifiers": [
              "Shift"
            ]
          }
        ]
      }
    ],
    "9": [
      {
        "sequence": [
          {
            "key": "Digit9",
            "modifiers": [
              "Shift"
            ]
          }
        ]
      }
    ],
    "¢": [
      {
        "sequence": [
          {
            "key": "KeyE",
            "modifiers": [
              "Shift",
              "AltGraph"
            ]
          }
        ]
      }
    ],
    "E": [
      {
        "sequence": [
          {
            "key": "KeyE",
            "modifiers": [
              "Shift"
            ]
          }
        ]
      }
    ],
    "8": [
      {
        "sequence": [
          {
            "key": "Digit8",
            "modifiers": [
              "Shift"
            ]
          }
        ]
      }
    ],
    "M": [
      {
        "sequence": [
          {
            "key": "Semicolon",
            "modifiers": [
              "Shift"
            ]
          }
        ]
      }
    ],
    "‑": [
      {
        "sequence": [
          {
            "key": "Digit6",
            "modifiers": [
              "Shift",
              "AltGraph"
            ]
          }
        ]
      }
    ],
    "“": [
      {
        "sequence": [
          {
            "key": "KeyZ",
            "modifiers": [
              "Shift",
              "AltGraph"
            ]
          }
        ]
      }
    ],
    "¬": [
      {
        "sequence": [
          {
            "key": "KeyN",
            "modifiers": [
              "AltGraph"
            ]
          }
        ]
      }
    ],
    "R": [
      {
        "sequence": [
          {
            "key": "KeyR",
            "modifiers": [
              "Shift"
            ]
          }
        ]
      }
    ],
    "þ": [
      {
        "sequence": [
          {
            "key": "KeyT",
            "modifiers": [
              "AltGraph"
            ]
          }
        ]
      }
    ],
    "Ä": [
      {
        "sequence": [
          {
            "key": "KeyA",
            "modifiers": [
              "Shift",
              "AltGraph"
            ]
          }
        ]
      }
    ],
    "~": [
      {
        "sequence": [
          {
            "key": "Digit2",
            "modifiers": [
              "AltGraph"
            ]
          }
        ]
      },
      {
        "sequence": [
          {
            "key": "BracketLeft",
            "modifiers": [
              "AltGraph"
            ]
          }
        ]
      }
    ],
    "%": [
      {
        "sequence": [
          {
            "key": "Quote",
            "modifiers": [
              "Shift"
            ]
          }
        ]
      }
    ],
    "⋅": [
      {
        "sequence": [
          {
            "key": "Comma",
            "modifiers": [
              "Shift",
              "AltGraph"
            ]
          }
        ]
      }
    ],
    "×": [
      {
        "sequence": [
          {
            "key": "Comma",
            "modifiers": [
              "AltGraph"
            ]
          }
        ]
      }
    ],
    "K": [
      {
        "sequence": [
          {
            "key": "KeyK",
            "modifiers": [
              "Shift"
            ]
          }
        ]
      }
    ],
    "/": [
      {
        "sequence": [
          {
            "key": "Period",
            "modifiers": [
              "Shift"
            ]
          }
        ]
      }
    ],
    "}": [
      {
        "sequence": [
          {
            "key": "Equal",
            "modifiers": [
              "AltGraph"
            ]
          }
        ]
      }
    ],
    "'": [
      {
        "sequence": [
          {
            "key": "Digit4",
            "modifiers": []
          }
        ]
      }
    ],
    "ß": [
      {
        "sequence": [
          {
            "key": "KeyS",
            "modifiers": [
              "AltGraph"
            ]
          }
        ]
      }
    ],
    "‘": [
      {
        "sequence": [
          {
            "key": "KeyF",
            "modifiers": [
              "AltGraph"
            ]
          }
        ]
      }
    ],
    "µ": [
      {
        "sequence": [
          {
            "key": "Backslash",
            "modifiers": [
              "Shift"
            ]
          }
        ]
      }
    ],
    "£": [
      {
        "sequence": [
          {
            "key": "BracketRight",
            "modifiers": [
              "Shift"
            ]
          }
        ]
      }
    ],
    ";": [
      {
        "sequence": [
          {
            "key": "Comma",
            "modifiers": []
          }
        ]
      }
    ],
    " ": [
      {
        "sequence": [
          {
            "key": "Space",
            "modifiers": [
              "Shift",
              "AltGraph"
            ]
          }
        ]
      }
    ],
    "#": [
      {
        "sequence": [
          {
            "key": "Digit3",
            "modifiers": [
              "AltGraph"
            ]
          }
        ]
      }
    ],
    "Î": [
      {
        "sequence": [
          {
            "key": "KeyI",
            "modifiers": [
              "Shift",
              "AltGraph"
            ]
          }
        ]
      }
    ],
    "P": [
      {
        "sequence": [
          {
            "key": "KeyP",
            "modifiers": [
              "Shift"
            ]
          }
        ]
      }
    ],
    "@": [
      {
        "sequence": [
          {
            "key": "Digit0",
            "modifiers": [
              "AltGraph"
            ]
          }
        ]
      }
    ],
    "é": [
      {
        "sequence": [
          {
            "key": "Digit2",
            "modifiers": []
          }
        ]
      }
    ],
    "y": [
      {
        "sequence": [
          {
            "key": "KeyY",
            "modifiers": []
          }
        ]
      }
    ],
    "=": [
      {
        "sequence": [
          {
            "key": "Equal",
            "modifiers": []
          }
        ]
      }
    ],
    "*": [
      {
        "sequence": [
          {
            "key": "Backslash",
            "modifiers": []
          }
        ]
      }
    ],
    "H": [
      {
        "sequence": [
          {
            "key": "KeyH",
            "modifiers": [
              "Shift"
            ]
          }
        ]
      }
    ],
    "Ö": [
      {
        "sequence": [
          {
            "key": "Semicolon",
            "modifiers": [
              "Shift",
              "AltGraph"
            ]
          }
        ]
      }
    ],
    "?": [
      {
        "sequence": [
          {
            "key": "KeyM",
            "modifiers": [
              "Shift"
            ]
          }
        ]
      }
    ],
    "e": [
      {
        "sequence": [
          {
            "key": "KeyE",
            "modifiers": []
          }
        ]
      }
    ],
    "[": [
      {
        "sequence": [
          {
            "key": "Digit5",
            "modifiers": [
              "AltGraph"
            ]
          }
        ]
      }
    ],
    "+": [
      {
        "sequence": [
          {
            "key": "Equal",
            "modifiers": [
              "Shift"
            ]
          }
        ]
      }
    ],
    "˘": [
      {
        "sequence": [
          {
            "key": "Digit3",
            "modifiers": [
              "Shift",
              "AltGraph"
            ]
          }
        ]
      }
    ],
    "5": [
      {
        "sequence": [
          {
            "key": "Digit5",
            "modifiers": [
              "Shift"
            ]
          }
        ]
      }
    ],
    "€": [
      {
        "sequence": [
          {
            "key": "KeyE",
            "modifiers": [
              "AltGraph"
            ]
          }
        ]
      }
    ],
    "j": [
      {
        "sequence": [
          {
            "key": "KeyJ",
            "modifiers": []
          }
        ]
      }
    ],
    "L": [
      {
        "sequence": [
          {
            "key": "KeyL",
            "modifiers": [
              "Shift"
            ]
          }
        ]
      }
    ],
    "6": [
      {
        "sequence": [
          {
            "key": "Digit6",
            "modifiers": [
              "Shift"
            ]
          }
        ]
      }
    ],
    "´": [
      {
        "sequence": [
          {
            "key": "Quote",
            "modifiers": [
              "AltGraph"
            ]
          }
        ]
      }
    ],
    "Y": [
      {
        "sequence": [
          {
            "key": "KeyY",
            "modifiers": [
              "Shift"
            ]
          }
        ]
      }
    ],
    ")": [
      {
        "sequence": [
          {
            "key": "Minus",
            "modifiers": []
          }
        ]
      }
    ],
    "]": [
      {
        "sequence": [
          {
            "key": "Minus",
            "modifiers": [
              "AltGraph"
            ]
          }
        ]
      }
    ],
    "d": [
      {
        "sequence": [
          {
            "key": "KeyD",
            "modifiers": []
          }
        ]
      }
    ],
    "§": [
      {
        "sequence": [
          {
            "key": "Slash",
            "modifiers": [
              "Shift"
            ]
          }
        ]
      }
    ],
    "¹": [
      {
        "sequence": [
          {
            "key": "Backquote",
            "modifiers": [
              "AltGraph"
            ]
          }
        ]
      }
    ],
    "¸": [
      {
        "sequence": [
          {
            "key": "Backquote",
            "modifiers": [
              "Shift",
              "AltGraph"
            ]
          }
        ]
      }
    ],
    "Ï": [
      {
        "sequence": [
          {
            "key": "KeyK",
            "modifiers": [
              "Shift",
              "AltGraph"
            ]
          }
        ]
      }
    ],
    "v": [
      {
        "sequence": [
          {
            "key": "KeyV",
            "modifiers": []
          }
        ]
      }
    ],
    "œ": [
      {
        "sequence": [
          {
            "key": "KeyO",
            "modifiers": [
              "AltGraph"
            ]
          }
        ]
      }
    ],
    "2": [
      {
        "sequence": [
          {
            "key": "Digit2",
            "modifiers": [
              "Shift"
            ]
          }
        ]
      }
    ],
    "Z": [
      {
        "sequence": [
          {
            "key": "KeyW",
            "modifiers": [
              "Shift"
            ]
          }
        ]
      }
    ],
    "Œ": [
      {
        "sequence": [
          {
            "key": "KeyO",
            "modifiers": [
              "Shift",
              "AltGraph"
            ]
          }
        ]
      }
    ],
    "−": [
      {
        "sequence": [
          {
            "key": "Slash",
            "modifiers": [
              "Shift",
              "AltGraph"
            ]
          }
        ]
      }
    ],
    "↓": [
      {
        "sequence": [
          {
            "key": "KeyB",
            "modifiers": [
              "AltGraph"
            ]
          }
        ]
      }
    ],
    "F": [
      {
        "sequence": [
          {
            "key": "KeyF",
            "modifiers": [
              "Shift"
            ]
          }
        ]
      }
    ],
    "J": [
      {
        "sequence": [
          {
            "key": "KeyJ",
            "modifiers": [
              "Shift"
            ]
          }
        ]
      }
    ],
    "…": [
      {
        "sequence": [
          {
            "key": "KeyM",
            "modifiers": [
              "Shift",
              "AltGraph"
            ]
          }
        ]
      }
    ],
    "q": [
      {
        "sequence": [
          {
            "key": "KeyA",
            "modifiers": []
          }
        ]
      }
    ],
    "↑": [
      {
        "sequence": [
          {
            "key": "KeyB",
            "modifiers": [
              "Shift",
              "AltGraph"
            ]
          }
        ]
      }
    ],
    "„": [
      {
        "sequence": [
          {
            "key": "KeyS",
            "modifiers": [
              "Shift",
              "AltGraph"
            ]
          }
        ]
      }
    ],
    "C": [
      {
        "sequence": [
          {
            "key": "KeyC",
            "modifiers": [
              "Shift"
            ]
          }
        ]
      }
    ],
    "Ç": [
      {
        "sequence": [
          {
            "key": "Digit9",
            "modifiers": [
              "Shift",
              "AltGraph"
            ]
          }
        ]
      }
    ],
    "→": [
      {
        "sequence": [
          {
            "key": "KeyN",
            "modifiers": [
              "Shift",
              "AltGraph"
            ]
          }
        ]
      }
    ],
    "Â": [
      {
        "sequence": [
          {
            "key": "KeyW",
            "modifiers": [
              "Shift",
              "AltGraph"
            ]
          }
        ]
      }
    ],
    "À": [
      {
        "sequence": [
          {
            "key": "Digit0",
            "modifiers": [
              "Shift",
              "AltGraph"
            ]
          }
        ]
      }
    ],
    "≤": [
      {
        "sequence": [
          {
            "key": "IntlBackslash",
            "modifiers": [
              "AltGraph"
            ]
          }
        ]
      }
    ],
    "°": [
      {
        "sequence": [
          {
            "key": "Minus",
            "modifiers": [
              "Shift"
            ]
          }
        ]
      }
    ],
    "S": [
      {
        "sequence": [
          {
            "key": "KeyS",
            "modifiers": [
              "Shift"
            ]
          }
        ]
      }
    ],
    "Ø": [
      {
        "sequence": [
          {
            "key": "BracketRight",
            "modifiers": [
              "Shift",
              "AltGraph"
            ]
          }
        ]
      }
    ],
    "à": [
      {
        "sequence": [
          {
            "key": "Digit0",
            "modifiers": []
          }
        ]
      }
    ],
    "ê": [
      {
        "sequence": [
          {
            "key": "KeyR",
            "modifiers": [
              "AltGraph"
            ]
          }
        ]
      }
    ],
    "u": [
      {
        "sequence": [
          {
            "key": "KeyU",
            "modifiers": []
          }
        ]
      }
    ],
    "&": [
      {
        "sequence": [
          {
            "key": "Digit1",
            "modifiers": []
          }
        ]
      }
    ],
    "U": [
      {
        "sequence": [
          {
            "key": "KeyU",
            "modifiers": [
              "Shift"
            ]
          }
        ]
      }
    ],
    "1": [
      {
        "sequence": [
          {
            "key": "Digit1",
            "modifiers": [
              "Shift"
            ]
          }
        ]
      }
    ],
    "ü": [
      {
        "sequence": [
          {
            "key": "KeyJ",
            "modifiers": [
              "AltGraph"
            ]
          }
        ]
      }
    ],
    "0": [
      {
        "sequence": [
          {
            "key": "Digit0",
            "modifiers": [
              "Shift"
            ]
          }
        ]
      }
    ],
    "w": [
      {
        "sequence": [
          {
            "key": "KeyZ",
            "modifiers": []
          }
        ]
      }
    ],
    "ç": [
      {
        "sequence": [
          {
            "key": "Digit9",
            "modifiers": []
          }
        ]
      }
    ],
    "m": [
      {
        "sequence": [
          {
            "key": "Semicolon",
            "modifiers": []
          }
        ]
      }
    ],
    "»": [
      {
        "sequence": [
          {
            "key": "KeyX",
            "modifiers": [
              "AltGraph"
            ]
          }
        ]
      }
    ],
    "3": [
      {
        "sequence": [
          {
            "key": "Digit3",
            "modifiers": [
              "Shift"
            ]
          }
        ]
      }
    ],
    "←": [
      {
        "sequence": [
          {
            "key": "KeyV",
            "modifiers": [
              "Shift",
              "AltGraph"
            ]
          }
        ]
      }
    ],
    "ä": [
      {
        "sequence": [
          {
            "key": "KeyA",
            "modifiers": [
              "AltGraph"
            ]
          }
        ]
      }
    ],
    "‚": [
      {
        "sequence": [
          {
            "key": "KeyF",
            "modifiers": [
              "Shift",
              "AltGraph"
            ]
          }
        ]
      }
    ],
    "ù": [
      {
        "sequence": [
          {
            "key": "Quote",
            "modifiers": []
          }
        ]
      }
    ],
    ",": [
      {
        "sequence": [
          {
            "key": "KeyM",
            "modifiers": []
          }
        ]
      }
    ],
    "<": [
      {
        "sequence": [
          {
            "key": "IntlBackslash",
            "modifiers": []
          }
        ]
      }
    ],
    "t": [
      {
        "sequence": [
          {
            "key": "KeyT",
            "modifiers": []
          }
        ]
      }
    ],
    "{": [
      {
        "sequence": [
          {
            "key": "Digit4",
            "modifiers": [
              "AltGraph"
            ]
          }
        ]
      }
    ],
    "ë": [
      {
        "sequence": [
          {
            "key": "KeyD",
            "modifiers": [
              "AltGraph"
            ]
          }
        ]
      }
    ],
    "É": [
      {
        "sequence": [
          {
            "key": "Digit2",
            "modifiers": [
              "Shift",
              "AltGraph"
            ]
          }
        ]
      }
    ],
    "l": [
      {
        "sequence": [
          {
            "key": "KeyL",
            "modifiers": []
          }
        ]
      }
    ],
    "¯": [
      {
        "sequence": [
          {
            "key": "Backslash",
            "modifiers": [
              "Shift",
              "AltGraph"
            ]
          }
        ]
      }
    ],
    "Ü": [
      {
        "sequence": [
          {
            "key": "KeyJ",
            "modifiers": [
              "Shift",
              "AltGraph"
            ]
          }
        ]
      }
    ],
    "Ù": [
      {
        "sequence": [
          {
            "key": "Quote",
            "modifiers": [
              "Shift",
              "AltGraph"
            ]
          }
        ]
      }
    ],
    "7": [
      {
        "sequence": [
          {
            "key": "Digit7",
            "modifiers": [
              "Shift"
            ]
          }
        ]
      }
    ],
    "V": [
      {
        "sequence": [
          {
            "key": "KeyV",
            "modifiers": [
              "Shift"
            ]
          }
        ]
      }
    ],
    "Ð": [
      {
        "sequence": [
          {
            "key": "KeyH",
            "modifiers": [
              "Shift",
              "AltGraph"
            ]
          }
        ]
      }
    ],
    "r": [
      {
        "sequence": [
          {
            "key": "KeyR",
            "modifiers": []
          }
        ]
      }
    ],
    "A": [
      {
        "sequence": [
          {
            "key": "KeyQ",
            "modifiers": [
              "Shift"
            ]
          }
        ]
      }
    ],
    "\"": [
      {
        "sequence": [
          {
            "key": "Digit3",
            "modifiers": []
          }
        ]
      }
    ],
    "Ô": [
      {
        "sequence": [
          {
            "key": "KeyP",
            "modifiers": [
              "Shift",
              "AltGraph"
            ]
          }
        ]
      }
    ]
  }
}