{
  "metadata": {
    "platform": "linux",
    "layout_name": "in",
    "extracted_on": "2026-07-06T23:13:58Z"
  },
  "mappings": {
    "2": [
      {
        "sequence": [
          {
            "key": "Digit2",
            "modifiers": [
              "AltGraph"
            ]
          }
        ]
      }
    ],
    "१": [
      {
        "sequence": [
          {
            "key": "Digit1",
            "modifiers": []
          }
        ]
      }
    ],
    "ॣ": [
      {
        "sequence": [
          {
            "key": "KeyR",
            "modifiers": [
              "AltGraph"
            ]
          }
        ]
      }
    ],
    "श": [
      {
        "sequence": [
          {
            "key": "KeyM",
            "modifiers": [
              "Shift"
            ]
          }
        ]
      }
    ],
    "छ": [
      {
        "sequence": [
          {
            "key": "Semicolon",
            "modifiers": [
              "Shift"
            ]
          }
        ]
      }
    ],
    "ॡ": [
      {
        "sequence": [
          {
            "key": "KeyR",
            "modifiers": [
              "Shift",
              "AltGraph"
            ]
          }
        ]
      }
    ],
    "ग": [
      {
        "sequence": [
          {
            "key": "KeyI",
            "modifiers": []
          }
        ]
      }
    ],
    "ॉ": [
      {
        "sequence": [
          {
            "key": "Backslash",
            "modifiers": []
          }
        ]
      }
    ],
    "्": [
      {
        "sequence": [
          {
            "key": "KeyD",
            "modifiers": []
          }
        ]
      }
    ],
    "॰": [
      {
        "sequence": [
          {
            "key": "Comma",
            "modifiers": [
              "AltGraph"
            ]
          }
        ]
      }
    ],
    "ढ़": [
      {
        "sequence": [
          {
            "key": "BracketLeft",
            "modifiers": [
              "Shift",
              "AltGraph"
            ]
          }
        ]
      }
    ],
    "भ": [
      {
        "sequence": [
          {
            "key": "KeyY",
            "modifiers": [
              "Shift"
            ]
          }
        ]
      }
    ],
    "3": [
      {
        "sequence": [
          {
            "key": "Digit3",
            "modifiers": [
              "AltGraph"
            ]
          }
        ]
      }
    ],
    "७": [
      {
        "sequence": [
          {
            "key": "Digit7",
            "modifiers": []
          }
        ]
      }
    ],
    "॒": [
      {
        "sequence": [
          {
            "key": "Semicolon",
            "modifiers": [
              "AltGraph"
            ]
          }
        ]
      }
    ],
    "/": [
      {
        "sequence": [
          {
            "key": "Slash",
            "modifiers": [
              "AltGraph"
            ]
          }
        ]
      }
    ],
    "ी": [
      {
        "sequence": [
          {
            "key": "KeyR",
            "modifiers": []
          }
        ]
      }
    ],
    "आ": [
      {
        "sequence": [
          {
            "key": "KeyE",
            "modifiers": [
              "Shift"
            ]
          }
        ]
      }
    ],
    "\\": [
      {
        "sequence": [
          {
            "key": "Backslash",
            "modifiers": [
              "AltGraph"
            ]
          }
        ]
      }
    ],
    "फ": [
      {
        "sequence": [
          {
            "key": "KeyH",
            "modifiers": [
              "Shift"
            ]
          }
        ]
      }
    ],
    "न": [
      {
        "sequence": [
          {
            "key": "KeyV",
            "modifiers": []
          }
        ]
      }
    ],
    "₹": [
      {
        "sequence": [
          {
            "key": "Digit4",
            "modifiers": [
              "Shift",
              "AltGraph"
            ]
          }
        ]
      }
    ],
    "ह": [
      {
        "sequence": [
          {
            "key": "KeyU",
            "modifiers": []
          }
        ]
      }
    ],
    "ठ": [
      {
        "sequence": [
          {
            "key": "Quote",
            "modifiers": [
              "Shift"
            ]
          }
        ]
      }
    ],
    "ॐ": [
      {
        "sequence": [
          {
            "key": "KeyX",
            "modifiers": [
              "Shift",
              "AltGraph"
            ]
          }
        ]
      }
    ],
    "ो": [
      {
        "sequence": [
          {
            "key": "KeyA",
            "modifiers": []
          }
        ]
      }
    ],
    "औ": [
      {
        "sequence": [
          {
            "key": "KeyQ",
            "modifiers": [
              "Shift"
            ]
          }
        ]
      }
    ],
    "5": [
      {
        "sequence": [
          {
            "key": "Digit5",
            "modifiers": [
              "AltGraph"
            ]
          }
        ]
      }
    ],
    "॓": [
      {
        "sequence": [
          {
            "key": "KeyZ",
            "modifiers": [
              "AltGraph"
            ]
          }
        ]
      }
    ],
    "<": [
      {
        "sequence": [
          {
            "key": "IntlBackslash",
            "modifiers": []
          }
        ]
      }
    ],
    "ऍ": [
      {
        "sequence": [
          {
            "key": "Digit1",
            "modifiers": [
              "Shift"
            ]
          }
        ]
      }
    ],
    ")": [
      {
        "sequence": [
          {
            "key": "Digit0",
            "modifiers": [
              "Shift"
            ]
          }
        ]
      },
      {
        "sequence": [
          {
            "key": "Digit0",
            "modifiers": [
              "Shift",
              "AltGraph"
            ]
          }
        ]
      }
    ],
    "झ": [
      {
        "sequence": [
          {
            "key": "KeyP",
            "modifiers": [
              "Shift"
            ]
          }
        ]
      }
    ],
    ">": [
      {
        "sequence": [
          {
            "key": "IntlBackslash",
            "modifiers": [
              "Shift"
            ]
          }
        ]
      }
    ],
    "ऌ": [
      {
        "sequence": [
          {
            "key": "KeyF",
            "modifiers": [
              "Shift",
              "AltGraph"
            ]
          }
        ]
      }
    ],
    "४": [
      {
        "sequence": [
          {
            "key": "Digit4",
            "modifiers": []
          }
        ]
      }
    ],
    "म": [
      {
        "sequence": [
          {
            "key": "KeyC",
            "modifiers": []
          }
        ]
      }
    ],
    "^": [
      {
        "sequence": [
          {
            "key": "Digit6",
            "modifiers": [
              "Shift"
            ]
          }
        ]
      },
      {
        "sequence": [
          {
            "key": "Digit6",
            "modifiers": [
              "Shift",
              "AltGraph"
            ]
          }
        ]
      }
    ],
    "ऩ": [
      {
        "sequence": [
          {
            "key": "KeyV",
            "modifiers": [
              "Shift"
            ]
          }
        ]
      }
    ],
    "‍": [
      {
        "sequence": [
          {
            "key": "Space",
            "modifiers": [
              "Shift",
              "AltGraph"
            ]
          }
        ]
      }
    ],
    "ग़": [
      {
        "sequence": [
          {
            "key": "KeyI",
            "modifiers": [
              "AltGraph"
            ]
          }
        ]
      }
    ],
    "ऊ": [
      {
        "sequence": [
          {
            "key": "KeyT",
            "modifiers": [
              "Shift"
            ]
          }
        ]
      }
    ],
    "अ": [
      {
        "sequence": [
          {
            "key": "KeyD",
            "modifiers": [
              "Shift"
            ]
          }
        ]
      }
    ],
    "॑": [
      {
        "sequence": [
          {
            "key": "Quote",
            "modifiers": [
              "Shift",
              "AltGraph"
            ]
          }
        ]
      }
    ],
    "-": [
      {
        "sequence": [
          {
            "key": "Minus",
            "modifiers": []
          }
        ]
      },
      {
        "sequence": [
          {
            "key": "Minus",
            "modifiers": [
              "AltGraph"
            ]
          }
        ]
      }
    ],
    "प": [
      {
        "sequence": [
          {
            "key": "KeyH",
            "modifiers": []
          }
        ]
      }
    ],
    "३": [
      {
        "sequence": [
          {
            "key": "Digit3",
            "modifiers": []
          }
        ]
      }
    ],
    "#": [
      {
        "sequence": [
          {
            "key": "Digit3",
            "modifiers": [
              "Shift"
            ]
          }
        ]
      },
      {
        "sequence": [
          {
            "key": "Digit3",
            "modifiers": [
              "Shift",
              "AltGraph"
            ]
          }
        ]
      }
    ],
    "7": [
      {
        "sequence": [
          {
            "key": "Digit7",
            "modifiers": [
              "AltGraph"
            ]
          }
        ]
      }
    ],
    "े": [
      {
        "sequence": [
          {
            "key": "KeyS",
            "modifiers": []
          }
        ]
      }
    ],
    "ड": [
      {
        "sequence": [
          {
            "key": "BracketLeft",
            "modifiers": []
          }
        ]
      }
    ],
    ".": [
      {
        "sequence": [
          {
            "key": "Period",
            "modifiers": []
          }
        ]
      }
    ],
    " ": [
      {
        "sequence": [
          {
            "key": "Space",
            "modifiers": []
          }
        ]
      },
      {
        "sequence": [
          {
            "key": "Space",
            "modifiers": [
              "Shift"
            ]
          }
        ]
      }
    ],
    "उ": [
      {
        "sequence": [
          {
            "key": "KeyG",
            "modifiers": [
              "Shift"
            ]
          }
        ]
      }
    ],
    "¦": [
      {
        "sequence": [
          {
            "key": "IntlBackslash",
            "modifiers": [
              "Shift",
              "AltGraph"
            ]
          }
        ]
      }
    ],
    "त": [
      {
        "sequence": [
          {
            "key": "KeyL",
            "modifiers": []
          }
        ]
      }
    ],
    "़": [
      {
        "sequence": [
          {
            "key": "BracketRight",
            "modifiers": []
          }
        ]
      }
    ],
    "र": [
      {
        "sequence": [
          {
            "key": "KeyJ",
            "modifiers": []
          }
        ]
      }
    ],
    "`": [
      {
        "sequence": [
          {
            "key": "Backquote",
            "modifiers": [
              "AltGraph"
            ]
          }
        ]
      }
    ],
    "ू": [
      {
        "sequence": [
          {
            "key": "KeyT",
            "modifiers": []
          }
        ]
      }
    ],
    "ञ": [
      {
        "sequence": [
          {
            "key": "BracketRight",
            "modifiers": [
              "Shift"
            ]
          }
        ]
      }
    ],
    "*": [
      {
        "sequence": [
          {
            "key": "Digit8",
            "modifiers": [
              "Shift"
            ]
          }
        ]
      },
      {
        "sequence": [
          {
            "key": "Digit8",
            "modifiers": [
              "Shift",
              "AltGraph"
            ]
          }
        ]
      }
    ],
    "ँ": [
      {
        "sequence": [
          {
            "key": "KeyX",
            "modifiers": [
              "Shift"
            ]
          }
        ]
      }
    ],
    "ै": [
      {
        "sequence": [
          {
            "key": "KeyW",
            "modifiers": []
          }
        ]
      }
    ],
    "य": [
      {
        "sequence": [
          {
            "key": "Slash",
            "modifiers": []
          }
        ]
      }
    ],
    "ऴ": [
      {
        "sequence": [
          {
            "key": "KeyB",
            "modifiers": [
              "Shift"
            ]
          }
        ]
      }
    ],
    "।": [
      {
        "sequence": [
          {
            "key": "Period",
            "modifiers": [
              "Shift"
            ]
          }
        ]
      }
    ],
    "4": [
      {
        "sequence": [
          {
            "key": "Digit4",
            "modifiers": [
              "AltGraph"
            ]
          }
        ]
      }
    ],
    "ढ": [
      {
        "sequence": [
          {
            "key": "BracketLeft",
            "modifiers": [
              "Shift"
            ]
          }
        ]
      }
    ],
    "५": [
      {
        "sequence": [
          {
            "key": "Digit5",
            "modifiers": []
          }
        ]
      }
    ],
    "०": [
      {
        "sequence": [
          {
            "key": "Digit0",
            "modifiers": []
          }
        ]
      }
    ],
    "ण": [
      {
        "sequence": [
          {
            "key": "KeyC",
            "modifiers": [
              "Shift"
            ]
          }
        ]
      }
    ],
    "&": [
      {
        "sequence": [
          {
            "key": "Digit7",
            "modifiers": [
              "Shift"
            ]
          }
        ]
      },
      {
        "sequence": [
          {
            "key": "Digit7",
            "modifiers": [
              "Shift",
              "AltGraph"
            ]
          }
        ]
      }
    ],
    "ौ": [
      {
        "sequence": [
          {
            "key": "KeyQ",
            "modifiers": []
          }
        ]
      }
    ],
    "ऱ": [
      {
        "sequence": [
          {
            "key": "KeyJ",
            "modifiers": [
              "Shift"
            ]
          }
        ]
      }
    ],
    "_": [
      {
        "sequence": [
          {
            "key": "Minus",
            "modifiers": [
              "Shift",
              "AltGraph"
            ]
          }
        ]
      }
    ],
    "ल": [
      {
        "sequence": [
          {
            "key": "KeyN",
            "modifiers": []
          }
        ]
      }
    ],
    ",": [
      {
        "sequence": [
          {
            "key": "Comma",
            "modifiers": []
          }
        ]
      }
    ],
    "क": [
      {
        "sequence": [
          {
            "key": "KeyK",
            "modifiers": []
          }
        ]
      }
    ],
    "व": [
      {
        "sequence": [
          {
            "key": "KeyB",
            "modifiers": []
          }
        ]
      }
    ],
    "ऽ": [
      {
        "sequence": [
          {
            "key": "Period",
            "modifiers": [
              "Shift",
              "AltGraph"
            ]
          }
        ]
      }
    ],
    "~": [
      {
        "sequence": [
          {
            "key": "Backquote",
            "modifiers": [
              "Shift",
              "AltGraph"
            ]
          }
        ]
      }
    ],
    "ि": [
      {
        "sequence": [
          {
            "key": "KeyF",
            "modifiers": []
          }
        ]
      }
    ],
    "ॆ": [
      {
        "sequence": [
          {
            "key": "KeyZ",
            "modifiers": []
          }
        ]
      }
    ],
    "‌": [
      {
        "sequence": [
          {
            "key": "Space",
            "modifiers": [
              "AltGraph"
            ]
          }
        ]
      }
    ],
    "फ़": [
      {
        "sequence": [
          {
            "key": "KeyH",
            "modifiers": [
              "Shift",
              "AltGraph"
            ]
          }
        ]
      }
    ],
    "ऒ": [
      {
        "sequence": [
          {
            "key": "Backquote",
            "modifiers": [
              "Shift"
            ]
          }
        ]
      }
    ],
    "ख़": [
      {
        "sequence": [
          {
            "key": "KeyK",
            "modifiers": [
              "Shift",
              "AltGraph"
            ]
          }
        ]
      }
    ],
    "ऎ": [
      {
        "sequence": [
          {
            "key": "KeyZ",
            "modifiers": [
              "Shift"
            ]
          }
        ]
      }
    ],
    "थ": [
      {
        "sequence": [
          {
            "key": "KeyL",
            "modifiers": [
              "Shift"
            ]
          }
        ]
      }
    ],
    "ट": [
      {
        "sequence": [
          {
            "key": "Quote",
            "modifiers": []
          }
        ]
      }
    ],
    "ः": [
      {
        "sequence": [
          {
            "key": "Minus",
            "modifiers": [
              "Shift"
            ]
          }
        ]
      }
    ],
    "क़": [
      {
        "sequence": [
          {
            "key": "KeyK",
            "modifiers": [
              "AltGraph"
            ]
          }
        ]
      }
    ],
    "ऋ": [
      {
        "sequence": [
          {
            "key": "Equal",
            "modifiers": [
              "Shift"
            ]
          }
        ]
      }
    ],
    "(": [
      {
        "sequence": [
          {
            "key": "Digit9",
            "modifiers": [
              "Shift"
            ]
          }
        ]
      },
      {
        "sequence": [
          {
            "key": "Digit9",
            "modifiers": [
              "Shift",
              "AltGraph"
            ]
          }
        ]
      }
    ],
    "9": [
      {
        "sequence": [
          {
            "key": "Digit9",
            "modifiers": [
              "AltGraph"
            ]
          }
        ]
      }
    ],
    "ज़": [
      {
        "sequence": [
          {
            "key": "KeyP",
            "modifiers": [
              "AltGraph"
            ]
          }
        ]
      }
    ],
    "ध": [
      {
        "sequence": [
          {
            "key": "KeyO",
            "modifiers": [
              "Shift"
            ]
          }
        ]
      }
    ],
    "ज": [
      {
        "sequence": [
          {
            "key": "KeyP",
            "modifiers": []
          }
        ]
      }
    ],
    "६": [
      {
        "sequence": [
          {
            "key": "Digit6",
            "modifiers": []
          }
        ]
      }
    ],
    "$": [
      {
        "sequence": [
          {
            "key": "Digit4",
            "modifiers": [
              "Shift"
            ]
          }
        ]
      }
    ],
    "ॄ": [
      {
        "sequence": [
          {
            "key": "Equal",
            "modifiers": [
              "AltGraph"
            ]
          }
        ]
      }
    ],
    "ॠ": [
      {
        "sequence": [
          {
            "key": "Equal",
            "modifiers": [
              "Shift",
              "AltGraph"
            ]
          }
        ]
      }
    ],
    "%": [
      {
        "sequence": [
          {
            "key": "Digit5",
            "modifiers": [
              "Shift"
            ]
          }
        ]
      },
      {
        "sequence": [
          {
            "key": "Digit5",
            "modifiers": [
              "Shift",
              "AltGraph"
            ]
          }
        ]
      }
    ],
    "ड़": [
      {
        "sequence": [
          {
            "key": "BracketLeft",
            "modifiers": [
              "AltGraph"
            ]
          }
        ]
      }
    ],
    "घ": [
      {
        "sequence": [
          {
            "key": "KeyI",
            "modifiers": [
              "Shift"
            ]
          }
        ]
      }
    ],
    "ब": [
      {
        "sequence": [
          {
            "key": "KeyY",
            "modifiers": []
          }
        ]
      }
    ],
    "ओ": [
      {
        "sequence": [
          {
            "key": "KeyA",
            "modifiers": [
              "Shift"
            ]
          }
        ]
      }
    ],
    "ळ": [
      {
        "sequence": [
          {
            "key": "KeyN",
            "modifiers": [
              "Shift"
            ]
          }
        ]
      }
    ],
    "॥": [
      {
        "sequence": [
          {
            "key": "Period",
            "modifiers": [
              "AltGraph"
            ]
          }
        ]
      }
    ],
    "९": [
      {
        "sequence": [
          {
            "key": "Digit9",
            "modifiers": []
          }
        ]
      }
    ],
    "ृ": [
      {
        "sequence": [
          {
            "key": "Equal",
            "modifiers": []
          }
        ]
      }
    ],
    "1": [
      {
        "sequence": [
          {
            "key": "Digit1",
            "modifiers": [
              "AltGraph"
            ]
          }
        ]
      }
    ],
    "6": [
      {
        "sequence": [
          {
            "key": "Digit6",
            "modifiers": [
              "AltGraph"
            ]
          }
        ]
      }
    ],
    "!": [
      {
        "sequence": [
          {
            "key": "Digit1",
            "modifiers": [
              "Shift",
              "AltGraph"
            ]
          }
        ]
      }
    ],
    "@": [
      {
        "sequence": [
          {
            "key": "Digit2",
            "modifiers": [
              "Shift",
              "AltGraph"
            ]
          }
        ]
      }
    ],
    "च": [
      {
        "sequence": [
          {
            "key": "Semicolon",
            "modifiers": []
          }
        ]
      }
    ],
    "ङ": [
      {
        "sequence": [
          {
            "key": "KeyU",
            "modifiers": [
              "Shift"
            ]
          }
        ]
      }
    ],
    "8": [
      {
        "sequence": [
          {
            "key": "Digit8",
            "modifiers": [
              "AltGraph"
            ]
          }
        ]
      }
    ],
    "ऐ": [
      {
        "sequence": [
          {
            "key": "KeyW",
            "modifiers": [
              "Shift"
            ]
          }
        ]
      }
    ],
    "ा": [
      {
        "sequence": [
          {
            "key": "KeyE",
            "modifiers": []
          }
        ]
      }
    ],
    "स": [
      {
        "sequence": [
          {
            "key": "KeyM",
            "modifiers": []
          }
        ]
      }
    ],
    "द": [
      {
        "sequence": [
          {
            "key": "KeyO",
            "modifiers": []
          }
        ]
      }
    ],
    "२": [
      {
        "sequence": [
          {
            "key": "Digit2",
            "modifiers": []
          }
        ]
      }
    ],
    "ॅ": [
      {
        "sequence": [
          {
            "key": "Digit2",
            "modifiers": [
              "Shift"
            ]
          }
        ]
      }
    ],
    "ऑ": [
      {
        "sequence": [
          {
            "key": "Backslash",
            "modifiers": [
              "Shift"
            ]
          }
        ]
      }
    ],
    "इ": [
      {
        "sequence": [
          {
            "key": "KeyF",
            "modifiers": [
              "Shift"
            ]
          }
        ]
      }
    ],
    "?": [
      {
        "sequence": [
          {
            "key": "Slash",
            "modifiers": [
              "Shift",
              "AltGraph"
            ]
          }
        ]
      }
    ],
    "ख": [
      {
        "sequence": [
          {
            "key": "KeyK",
            "modifiers": [
              "Shift"
            ]
          }
        ]
      }
    ],
    "ॊ": [
      {
        "sequence": [
          {
            "key": "Backquote",
            "modifiers": []
          }
        ]
      }
    ],
    "ए": [
      {
        "sequence": [
          {
            "key": "KeyS",
            "modifiers": [
              "Shift"
            ]
          }
        ]
      }
    ],
    "ु": [
      {
        "sequence": [
          {
            "key": "KeyG",
            "modifiers": []
          }
        ]
      }
    ],
    "ष": [
      {
        "sequence": [
          {
            "key": "Comma",
            "modifiers": [
              "Shift"
            ]
          }
        ]
      }
    ],
    "ई": [
      {
        "sequence": [
          {
            "key": "KeyR",
            "modifiers": [
              "Shift"
            ]
          }
        ]
      }
    ],
    "0": [
      {
        "sequence": [
          {
            "key": "Digit0",
            "modifiers": [
              "AltGraph"
            ]
          }
        ]
      }
    ],
    "|": [
      {
        "sequence": [
          {
            "key": "Backslash",
            "modifiers": [
              "Shift",
              "AltGraph"
            ]
          }
        ]
      },
      {
        "sequence": [
          {
            "key": "IntlBackslash",
            "modifiers": [
              "AltGraph"
            ]
          }
        ]
      }
    ],
    "य़": [
      {
        "sequence": [
          {
            "key": "Slash",
            "modifiers": [
              "Shift"
            ]
          }
        ]
      }
    ],
    "ॢ": [
      {
        "sequence": [
          {
            "key": "KeyF",
            "modifiers": [
              "AltGraph"
            ]
          }
        ]
      }
    ],
    "॔": [
      {
        "sequence": [
          {
            "key": "KeyC",
            "modifiers": [
              "AltGraph"
            ]
          }
        ]
      }
    ],
    "८": [
      {
        "sequence": [
          {
            "key": "Digit8",
            "modifiers": []
          }
        ]
      }
    ],
    "ं": [
      {
        "sequence": [
          {
            "key": "KeyX",
            "modifiers": []
          }
        ]
      }
    ]
  }
}