{
  "metadata": {
    "platform": "linux",
    "layout_name": "th",
    "layout_variant": "tis",
    "display_name": "Thai (TIS-820.2538)",
    "extracted_on": "2026-07-07T01:15:30Z"
  },
  "mappings": {
    "ง": [
      {
        "sequence": [
          {
            "key": "Quote",
            "modifiers": []
          }
        ]
      }
    ],
    "|": [
      {
        "sequence": [
          {
            "key": "IntlBackslash",
            "modifiers": [
              "AltGraph"
            ]
          }
        ]
      }
    ],
    "๓": [
      {
        "sequence": [
          {
            "key": "Digit4",
            "modifiers": [
              "Shift"
            ]
          }
        ]
      }
    ],
    "ร": [
      {
        "sequence": [
          {
            "key": "KeyI",
            "modifiers": []
          }
        ]
      }
    ],
    "๎": [
      {
        "sequence": [
          {
            "key": "Digit7",
            "modifiers": [
              "Shift"
            ]
          }
        ]
      }
    ],
    "ู": [
      {
        "sequence": [
          {
            "key": "Digit6",
            "modifiers": [
              "Shift"
            ]
          }
        ]
      }
    ],
    "ฉ": [
      {
        "sequence": [
          {
            "key": "KeyC",
            "modifiers": [
              "Shift"
            ]
          }
        ]
      }
    ],
    "์": [
      {
        "sequence": [
          {
            "key": "KeyN",
            "modifiers": [
              "Shift"
            ]
          }
        ]
      }
    ],
    "?": [
      {
        "sequence": [
          {
            "key": "KeyM",
            "modifiers": [
              "Shift"
            ]
          }
        ]
      }
    ],
    "ฒ": [
      {
        "sequence": [
          {
            "key": "Comma",
            "modifiers": [
              "Shift"
            ]
          }
        ]
      }
    ],
    "ภ": [
      {
        "sequence": [
          {
            "key": "Digit4",
            "modifiers": []
          }
        ]
      }
    ],
    "๙": [
      {
        "sequence": [
          {
            "key": "Equal",
            "modifiers": [
              "Shift"
            ]
          }
        ]
      }
    ],
    "ท": [
      {
        "sequence": [
          {
            "key": "KeyM",
            "modifiers": []
          }
        ]
      }
    ],
    "๗": [
      {
        "sequence": [
          {
            "key": "Digit0",
            "modifiers": [
              "Shift"
            ]
          }
        ]
      }
    ],
    "๚": [
      {
        "sequence": [
          {
            "key": "KeyO",
            "modifiers": [
              "AltGraph"
            ]
          }
        ]
      }
    ],
    " ": [
      {
        "sequence": [
          {
            "key": "Space",
            "modifiers": []
          }
        ]
      }
    ],
    "อ": [
      {
        "sequence": [
          {
            "key": "KeyV",
            "modifiers": []
          }
        ]
      }
    ],
    "ส": [
      {
        "sequence": [
          {
            "key": "KeyL",
            "modifiers": []
          }
        ]
      }
    ],
    "ฆ": [
      {
        "sequence": [
          {
            "key": "KeyS",
            "modifiers": [
              "Shift"
            ]
          }
        ]
      }
    ],
    "ฮ": [
      {
        "sequence": [
          {
            "key": "KeyV",
            "modifiers": [
              "Shift"
            ]
          }
        ]
      }
    ],
    "ฃ": [
      {
        "sequence": [
          {
            "key": "Backslash",
            "modifiers": [
              "Shift"
            ]
          }
        ]
      }
    ],
    "ฎ": [
      {
        "sequence": [
          {
            "key": "KeyE",
            "modifiers": [
              "Shift"
            ]
          }
        ]
      }
    ],
    "ต": [
      {
        "sequence": [
          {
            "key": "Digit9",
            "modifiers": []
          }
        ]
      }
    ],
    "ณ": [
      {
        "sequence": [
          {
            "key": "KeyI",
            "modifiers": [
              "Shift"
            ]
          }
        ]
      }
    ],
    "น": [
      {
        "sequence": [
          {
            "key": "KeyO",
            "modifiers": []
          }
        ]
      }
    ],
    ",": [
      {
        "sequence": [
          {
            "key": "BracketRight",
            "modifiers": [
              "Shift"
            ]
          }
        ]
      }
    ],
    "็": [
      {
        "sequence": [
          {
            "key": "KeyH",
            "modifiers": [
              "Shift"
            ]
          }
        ]
      }
    ],
    "ฯ": [
      {
        "sequence": [
          {
            "key": "KeyO",
            "modifiers": [
              "Shift"
            ]
          }
        ]
      }
    ],
    "ฝ": [
      {
        "sequence": [
          {
            "key": "Slash",
            "modifiers": []
          }
        ]
      }
    ],
    "ิ": [
      {
        "sequence": [
          {
            "key": "KeyB",
            "modifiers": []
          }
        ]
      }
    ],
    "ฐ": [
      {
        "sequence": [
          {
            "key": "BracketLeft",
            "modifiers": [
              "Shift"
            ]
          }
        ]
      }
    ],
    "ฌ": [
      {
        "sequence": [
          {
            "key": "KeyG",
            "modifiers": [
              "Shift"
            ]
          }
        ]
      }
    ],
    ")": [
      {
        "sequence": [
          {
            "key": "KeyX",
            "modifiers": [
              "Shift"
            ]
          }
        ]
      }
    ],
    "ะ": [
      {
        "sequence": [
          {
            "key": "KeyT",
            "modifiers": []
          }
        ]
      }
    ],
    "ษ": [
      {
        "sequence": [
          {
            "key": "KeyK",
            "modifiers": [
              "Shift"
            ]
          }
        ]
      }
    ],
    "ป": [
      {
        "sequence": [
          {
            "key": "KeyX",
            "modifiers": []
          }
        ]
      }
    ],
    "ญ": [
      {
        "sequence": [
          {
            "key": "KeyP",
            "modifiers": [
              "Shift"
            ]
          }
        ]
      }
    ],
    "ฦ": [
      {
        "sequence": [
          {
            "key": "Slash",
            "modifiers": [
              "Shift"
            ]
          }
        ]
      }
    ],
    "จ": [
      {
        "sequence": [
          {
            "key": "Digit0",
            "modifiers": []
          }
        ]
      }
    ],
    "ไ": [
      {
        "sequence": [
          {
            "key": "KeyW",
            "modifiers": []
          }
        ]
      }
    ],
    "๊": [
      {
        "sequence": [
          {
            "key": "KeyU",
            "modifiers": [
              "Shift"
            ]
          }
        ]
      }
    ],
    "ห": [
      {
        "sequence": [
          {
            "key": "KeyS",
            "modifiers": []
          }
        ]
      }
    ],
    "ฑ": [
      {
        "sequence": [
          {
            "key": "KeyR",
            "modifiers": [
              "Shift"
            ]
          }
        ]
      }
    ],
    "/": [
      {
        "sequence": [
          {
            "key": "Digit2",
            "modifiers": []
          }
        ]
      }
    ],
    "้": [
      {
        "sequence": [
          {
            "key": "KeyH",
            "modifiers": []
          }
        ]
      }
    ],
    "ผ": [
      {
        "sequence": [
          {
            "key": "KeyZ",
            "modifiers": []
          }
        ]
      }
    ],
    "ี": [
      {
        "sequence": [
          {
            "key": "KeyU",
            "modifiers": []
          }
        ]
      }
    ],
    "ธ": [
      {
        "sequence": [
          {
            "key": "KeyT",
            "modifiers": [
              "Shift"
            ]
          }
        ]
      }
    ],
    "(": [
      {
        "sequence": [
          {
            "key": "KeyZ",
            "modifiers": [
              "Shift"
            ]
          }
        ]
      }
    ],
    "ฺ": [
      {
        "sequence": [
          {
            "key": "KeyB",
            "modifiers": [
              "Shift"
            ]
          }
        ]
      }
    ],
    "ึ": [
      {
        "sequence": [
          {
            "key": "Digit7",
            "modifiers": []
          }
        ]
      }
    ],
    "ๆ": [
      {
        "sequence": [
          {
            "key": "KeyQ",
            "modifiers": []
          }
        ]
      }
    ],
    ".": [
      {
        "sequence": [
          {
            "key": "Quote",
            "modifiers": [
              "Shift"
            ]
          }
        ]
      }
    ],
    "พ": [
      {
        "sequence": [
          {
            "key": "KeyR",
            "modifiers": []
          }
        ]
      }
    ],
    "๋": [
      {
        "sequence": [
          {
            "key": "KeyJ",
            "modifiers": [
              "Shift"
            ]
          }
        ]
      }
    ],
    "ื": [
      {
        "sequence": [
          {
            "key": "KeyN",
            "modifiers": []
          }
        ]
      }
    ],
    "ฬ": [
      {
        "sequence": [
          {
            "key": "Period",
            "modifiers": [
              "Shift"
            ]
          }
        ]
      }
    ],
    "บ": [
      {
        "sequence": [
          {
            "key": "BracketLeft",
            "modifiers": []
          }
        ]
      }
    ],
    "ฅ": [
      {
        "sequence": [
          {
            "key": "Backslash",
            "modifiers": []
          }
        ]
      }
    ],
    "๏": [
      {
        "sequence": [
          {
            "key": "Backquote",
            "modifiers": []
          }
        ]
      }
    ],
    "฿": [
      {
        "sequence": [
          {
            "key": "Digit1",
            "modifiers": []
          }
        ]
      }
    ],
    "ๅ": [
      {
        "sequence": [
          {
            "key": "Digit1",
            "modifiers": [
              "Shift"
            ]
          }
        ]
      }
    ],
    "ฟ": [
      {
        "sequence": [
          {
            "key": "KeyA",
            "modifiers": []
          }
        ]
      }
    ],
    "ก": [
      {
        "sequence": [
          {
            "key": "KeyD",
            "modifiers": []
          }
        ]
      }
    ],
    "๐": [
      {
        "sequence": [
          {
            "key": "KeyQ",
            "modifiers": [
              "Shift"
            ]
          }
        ]
      }
    ],
    "เ": [
      {
        "sequence": [
          {
            "key": "KeyG",
            "modifiers": []
          }
        ]
      }
    ],
    "๔": [
      {
        "sequence": [
          {
            "key": "Digit5",
            "modifiers": [
              "Shift"
            ]
          }
        ]
      }
    ],
    "๕": [
      {
        "sequence": [
          {
            "key": "Digit8",
            "modifiers": [
              "Shift"
            ]
          }
        ]
      }
    ],
    "๒": [
      {
        "sequence": [
          {
            "key": "Digit3",
            "modifiers": [
              "Shift"
            ]
          }
        ]
      }
    ],
    "๘": [
      {
        "sequence": [
          {
            "key": "Minus",
            "modifiers": [
              "Shift"
            ]
          }
        ]
      }
    ],
    "\"": [
      {
        "sequence": [
          {
            "key": "KeyW",
            "modifiers": [
              "Shift"
            ]
          }
        ]
      }
    ],
    "ั": [
      {
        "sequence": [
          {
            "key": "KeyY",
            "modifiers": []
          }
        ]
      }
    ],
    "ํ": [
      {
        "sequence": [
          {
            "key": "KeyY",
            "modifiers": [
              "Shift"
            ]
          }
        ]
      }
    ],
    "ถ": [
      {
        "sequence": [
          {
            "key": "Digit5",
            "modifiers": []
          }
        ]
      }
    ],
    "ย": [
      {
        "sequence": [
          {
            "key": "KeyP",
            "modifiers": []
          }
        ]
      }
    ],
    "-": [
      {
        "sequence": [
          {
            "key": "Digit3",
            "modifiers": []
          }
        ]
      }
    ],
    "ล": [
      {
        "sequence": [
          {
            "key": "BracketRight",
            "modifiers": []
          }
        ]
      }
    ],
    "๛": [
      {
        "sequence": [
          {
            "key": "Backquote",
            "modifiers": [
              "Shift"
            ]
          }
        ]
      }
    ],
    "ด": [
      {
        "sequence": [
          {
            "key": "KeyF",
            "modifiers": []
          }
        ]
      }
    ],
    "๑": [
      {
        "sequence": [
          {
            "key": "Digit2",
            "modifiers": [
              "Shift"
            ]
          }
        ]
      }
    ],
    "๖": [
      {
        "sequence": [
          {
            "key": "Digit9",
            "modifiers": [
              "Shift"
            ]
          }
        ]
      }
    ],
    "่": [
      {
        "sequence": [
          {
            "key": "KeyJ",
            "modifiers": []
          }
        ]
      }
    ],
    "ศ": [
      {
        "sequence": [
          {
            "key": "KeyL",
            "modifiers": [
              "Shift"
            ]
          }
        ]
      }
    ],
    "ว": [
      {
        "sequence": [
          {
            "key": "Semicolon",
            "modifiers": []
          }
        ]
      }
    ],
    "ำ": [
      {
        "sequence": [
          {
            "key": "KeyE",
            "modifiers": []
          }
        ]
      }
    ],
    "ช": [
      {
        "sequence": [
          {
            "key": "Equal",
            "modifiers": []
          }
        ]
      }
    ],
    "ซ": [
      {
        "sequence": [
          {
            "key": "Semicolon",
            "modifiers": [
              "Shift"
            ]
          }
        ]
      }
    ],
    "ม": [
      {
        "sequence": [
          {
            "key": "Comma",
            "modifiers": []
          }
        ]
      }
    ],
    "ใ": [
      {
        "sequence": [
          {
            "key": "Period",
            "modifiers": []
          }
        ]
      }
    ],
    ">": [
      {
        "sequence": [
          {
            "key": "IntlBackslash",
            "modifiers": [
              "Shift"
            ]
          }
        ]
      }
    ],
    "¦": [
      {
        "sequence": [
          {
            "key": "IntlBackslash",
            "modifiers": [
              "Shift",
              "AltGraph"
            ]
          }
        ]
      }
    ],
    "า": [
      {
        "sequence": [
          {
            "key": "KeyK",
            "modifiers": []
          }
        ]
      }
    ],
    "ฏ": [
      {
        "sequence": [
          {
            "key": "KeyD",
            "modifiers": [
              "Shift"
            ]
          }
        ]
      }
    ],
    "ข": [
      {
        "sequence": [
          {
            "key": "Minus",
            "modifiers": []
          }
        ]
      }
    ],
    "โ": [
      {
        "sequence": [
          {
            "key": "KeyF",
            "modifiers": [
              "Shift"
            ]
          }
        ]
      }
    ],
    "แ": [
      {
        "sequence": [
          {
            "key": "KeyC",
            "modifiers": []
          }
        ]
      }
    ],
    "ฤ": [
      {
        "sequence": [
          {
            "key": "KeyA",
            "modifiers": [
              "Shift"
            ]
          }
        ]
      }
    ],
    "ุ": [
      {
        "sequence": [
          {
            "key": "Digit6",
            "modifiers": []
          }
        ]
      }
    ],
    "ค": [
      {
        "sequence": [
          {
            "key": "Digit8",
            "modifiers": []
          }
        ]
      }
    ],
    "<": [
      {
        "sequence": [
          {
            "key": "IntlBackslash",
            "modifiers": []
          }
        ]
      }
    ]
  }
}